Workbook
Name coeff_c_2CCEE246_9945_2140_BC14_9589485B31D0_0fd1f8c5_b793_4c6a_9738_c66d803607aa: '⚡ Leads'!$E$1
Name coeff_c_2CCEE246_9945_2140_BC14_9589485B31D0_58516334_2b0d_4bb8_aa1c_0da7fb0a08c6: '⚡ Leads'!$C$1
Name coeff_c_2CCEE246_9945_2140_BC14_9589485B31D0_954a83f1_e415_4d27_a772_8102e6b33558: '⚡ Leads'!$A$1
Name coeff_c_2CCEE246_9945_2140_BC14_9589485B31D0_987b5bcd_927e_41fb_8970_a5873b232b32: '⚡ Leads'!$B$1
Name coeff_c_2CCEE246_9945_2140_BC14_9589485B31D0_9d1a4a82_19a1_4650_aee1_73e43e206df3: '⚡ Leads'!$D$1
Name coeff_c_344D56EE_B9FC_084D_94CF_57A89FF39BC0_1ce7ea6a_8d9a_476f_8684_125e69f5434a: '⚡ Events'!$C$1
Name coeff_c_344D56EE_B9FC_084D_94CF_57A89FF39BC0_4e562cd5_7fc1_4160_88e6_7c20ee69e91e: '⚡ Events'!$A$1
Name coeff_c_344D56EE_B9FC_084D_94CF_57A89FF39BC0_9032b6c4_5674_4fdc_ba1d_b91c5be50b04: '⚡ Events'!$B$1
Name coeff_c_F6318C9D_BBC0_EF40_B911_3F41904FB1C5_0e358f63_a122_4840_86d6_ac397a19fc14: '⚡ Opportunities'!$B$1
Name coeff_c_F6318C9D_BBC0_EF40_B911_3F41904FB1C5_113d515e_ed67_45e5_8d65_b057dab81bb2: '⚡ Opportunities'!$F$1
Name coeff_c_F6318C9D_BBC0_EF40_B911_3F41904FB1C5_3e86d35e_9779_4adc_b01d_2bb75b6831a8: '⚡ Opportunities'!$E$1
Name coeff_c_F6318C9D_BBC0_EF40_B911_3F41904FB1C5_c2ab382a_94ad_4a4b_ae6b_6de2d30e8c6f: '⚡ Opportunities'!$H$1
Name coeff_c_F6318C9D_BBC0_EF40_B911_3F41904FB1C5_caf804c6_7a8f_4a4e_8ea0_18501cd7ebca: '⚡ Opportunities'!$A$1
Name coeff_c_F6318C9D_BBC0_EF40_B911_3F41904FB1C5_e537817c_237c_438a_aa64_49e98588f5db: '⚡ Opportunities'!$C$1
Name coeff_c_F6318C9D_BBC0_EF40_B911_3F41904FB1C5_ec93bc13_b4de_4d67_b931_521c4f5a2fb6: '⚡ Opportunities'!$G$1
Name coeff_c_F6318C9D_BBC0_EF40_B911_3F41904FB1C5_f9d174cc_4991_4aa3_bb12_8eba789fc966: '⚡ Opportunities'!$D$1
Name coeff_import_id: '⚡ Events'!#REF!
Name coeff_import_id: '⚡ Leads'!#REF!
Name coeff_import_id: '⚡ Opportunities'!#REF!
Name coeff_tpl_name: #REF!

Sheet ⚡ Leads
A1: First Name | B1: Last Name | C1: Company | D1: Created Date | E1: Status
A2: Kase | B2: Perez | C2: Account Jennings981 | D2: =TODAY()-737 -> 45300 | E2: Product Qualified Lead
A3: Sophia | B3: Nguyen | C3: Account Stokes949XX - new - new | D3: =TODAY()-737 -> 45300 | E3: Marketing Qualified Lead
A4: Kayden | B4: Hayes | C4: Account Leonard584X | D4: =TODAY()-737 -> 45300 | E4: Sales Qualified Lead
A5: Karson | B5: Parker | C5: Account Daniels627XX - new | D5: =TODAY()-737 -> 45300 | E5: Opportunity
A6: Faith | B6: Simmons | C6: Account Robbins1143 | D6: =TODAY()-737 -> 45300 | E6: Opportunity
A7: Ryder | B7: Adams | C7: Account Watson1794 | D7: =TODAY()-737 -> 45300 | E7: Sales Qualified Lead
A8: Mia | B8: Thompson | C8: Account Abbott1184X | D8: =TODAY()-737 -> 45300 | E8: Product Qualified Lead
A9: Kade | B9: Martinez | C9: Account Cross1834 - | D9: =TODAY()-737 -> 45300 | E9: Marketing Qualified Lead
A10: Kaia | B10: Hayes | C10: Account Perkins1263 - new | D10: =TODAY()-737 -> 45300 | E10: Opportunity
A11: Cason | B11: Parker | C11: Account Johnson1707XXX | D11: =TODAY()-737 -> 45300 | E11: Lead
A12: Julian | B12: Campbell | C12: Account Cross1834 | D12: =TODAY()-737 -> 45300 | E12: Customer
A13: Ariana | B13: Rivera | C13: Account McCormick23 | D13: =TODAY()-737 -> 45300 | E13: Opportunity
... A61: Christian | B61: Russell | C61: Account Rice1187 - new - new | D61: =TODAY()-737 -> 45300 | E61: Opportunity
A62: Kallie | B62: Murphy | C62: Account Rice1187XX | D62: =TODAY()-707 -> 45330 | E62: Customer
A63: Harper | B63: Rodriguez | C63: Account Olson321XX | D63: =TODAY()-707 -> 45330 | E63: Opportunity
A64: Kenna | B64: Martinez | C64: Account Gordon852XX - new - new | D64: =TODAY()-707 -> 45330 | E64: Opportunity
A65: Jayse | B65: Carter | C65: Account Cobb1406X | D65: =TODAY()-707 -> 45330 | E65: Lead
A66: Kaleigh | B66: Thompson | C66: Account Watson1794X | D66: =TODAY()-707 -> 45330 | E66: Sales Qualified Lead
A67: Jovanni | B67: Bennett | C67: Account Wise361XX - new | D67: =TODAY()-707 -> 45330 | E67: Opportunity
A68: Kai | B68: Adams | C68: Account Malone1334X - new | D68: =TODAY()-707 -> 45330 | E68: Product Qualified Lead
A69: Mackenzie | B69: Diaz | C69: Account Abbott1184 | D69: =TODAY()-707 -> 45330 | E69: Lead
A70: Kaysen | B70: Johnson | C70: Account Abbott1 | D70: =TODAY()-707 -> 45330 | E70: Product Qualified Lead
A71: Andi | B71: Brooks | C71: Account Watson1794XX | D71: =TODAY()-707 -> 45330 | E71: Lead
A72: Desmond | B72: Parker | C72: Account McCormick23 - new | D72: =TODAY()-707 -> 45330 | E72: Customer
A73: Keaton | B73: Perez | C73: Account Hamilton8 - new | D73: =TODAY()-707 -> 45330 | E73: Sales Qualified Lead
... A124: Eli | B124: Ward | C124: Account Klein1486XX | D124: =TODAY()-707 -> 45330 | E124: Product Qualified Lead
A125: Harper | B125: Rodriguez | C125: Account Olson321XX | D125: =TODAY()-676 -> 45361 | E125: Opportunity
A126: Kailani | B126: Scott | C126: Account Release | D126: =TODAY()-676 -> 45361 | E126: Opportunity
A127: Malcolm | B127: Reed | C127: Account Cobb1406XXX | D127: =TODAY()-676 -> 45361 | E127: Opportunity
A128: Kaliyah | B128: Hernandez | C128: McCormick and Sons | D128: =TODAY()-676 -> 45361 | E128: Opportunity
A129: Andrew | B129: Coleman | C129: Account Elliott511X | D129: =TODAY()-676 -> 45361 | E129: Customer
A130: Camille | B130: Rodriguez | C130: Account Spencer1223 - new | D130: =TODAY()-676 -> 45361 | E130: Customer
A131: Karsyn | B131: Bennett | C131: Account Hardy1 - new | D131: =TODAY()-676 -> 45361 | E131: Customer
A132: Luis | B132: Martinez | C132: Account Christensen | D132: =TODAY()-676 -> 45361 | E132: Sales Qualified Lead
A133: Kobe | B133: Campbell | C133: Account Todd162XXX | D133: =TODAY()-676 -> 45361 | E133: Opportunity
A134: Isla | B134: Phillips | C134: Account Conner5XX - new | D134: =TODAY()-676 -> 45361 | E134: Customer
A135: Alana | B135: Butler | C135: Account Olson321XX | D135: =TODAY()-676 -> 45361 | E135: Product Qualified Lead
A136: Luis | B136: Martinez | C136: Account Christensen | D136: =TODAY()-676 -> 45361 | E136: Sales Qualified Lead
... A191: Victoria | B191: Hayes | C191: Account Watson1794X | D191: =TODAY()-676 -> 45361 | E191: Sales Qualified Lead
A192: Kael | B192: Martinez | C192: Account Leonard584X - new | D192: =TODAY()-646 -> 45391 | E192: Customer
A193: Aubri | B193: Wright | C193: Account Estrada957 | D193: =TODAY()-646 -> 45391 | E193: Opportunity
A194: Grady | B194: Perez | C194: Account Frazier196X - new | D194: =TODAY()-646 -> 45391 | E194: Sales Qualified Lead
A195: Keaton | B195: Perez | C195: Account Hamilton8 - new | D195: =TODAY()-646 -> 45391 | E195: Sales Qualified Lead
A196: Miracle | B196: Hayes | C196: Account Spencer1223XX - new | D196: =TODAY()-646 -> 45391 | E196: Customer
A197: Sierra | B197: Evans | C197: Account Adams87 - new | D197: =TODAY()-646 -> 45391 | E197: Lead
A198: Abigail | B198: Scott | C198: Account Howard1207X | D198: =TODAY()-646 -> 45391 | E198: Customer
A199: Agustin | B199: Perez | C199: Account Guzman1793X | D199: =TODAY()-646 -> 45391 | E199: Customer
A200: Kendra | B200: Brooks | C200: Account Perkins1263 | D200: =TODAY()-646 -> 45391 | E200: Lead
A201: Luis | B201: Cooper | C201: Account Bass1237XX - new | D201: =TODAY()-646 -> 45391 | E201: Sales Qualified Lead
A202: Aria | B202: Ross | C202: Account New test opp | D202: =TODAY()-646 -> 45391 | E202: Opportunity
A203: Anika | B203: Hernandez | C203: Account Burton1994XX | D203: =TODAY()-646 -> 45391 | E203: Lead
... A262: Gemma | B262: Murphy | C262: Account Bates1455XX - new | D262: =TODAY()-646 -> 45391 | E262: Opportunity
A263: Jakobe | B263: Wright | C263: Account Leonard584XX - new | D263: =TODAY()-615 -> 45422 | E263: Lead
A264: Kyree | B264: Parker | C264: Account Stokes949XX | D264: =TODAY()-615 -> 45422 | E264: Sales Qualified Lead
A265: Jordan | B265: Cook | C265: Account Barton1670X | D265: =TODAY()-615 -> 45422 | E265: Customer
A266: Adeline | B266: Thompson | C266: ACME Corp | D266: =TODAY()-615 -> 45422 | E266: Sales Qualified Lead
A267: Nova | B267: Russell | C267: Account Carol - new - new | D267: =TODAY()-615 -> 45422 | E267: Lead
A268: Kaison | B268: Campbell | C268: Account Santiago1975XX - new | D268: =TODAY()-615 -> 45422 | E268: Product Qualified Lead
A269: Luciano | B269: Wright | C269: Account Wilkins1370 - new | D269: =TODAY()-615 -> 45422 | E269: Customer
A270: Leilani | B270: Hayes | C270: Account Barber186 | D270: =TODAY()-615 -> 45422 | E270: Customer
A271: Luna | B271: Bryant | C271: Account Collier5 - | D271: =TODAY()-615 -> 45422 | E271: Opportunity
A272: Joshua | B272: Perry | C272: Account Reyes - new | D272: =TODAY()-615 -> 45422 | E272: Customer
A273: Landon | B273: Allen | C273: Account Leonard584XX | D273: =TODAY()-615 -> 45422 | E273: Marketing Qualified Lead
A274: Adeline | B274: Thompson | C274: ACME Corp | D274: =TODAY()-615 -> 45422 | E274: Sales Qualified Lead
... A337: Hayden | B337: Gonzalez | C337: Account Burton1994X | D337: =TODAY()-615 -> 45422 | E337: Lead
A338: Jocelyn | B338: Thompson | C338: Account Olson321 | D338: =TODAY()-584 -> 45453 | E338: Lead
A339: Ethan | B339: Howard | C339: Account Adams87X - | D339: =TODAY()-584 -> 45453 | E339: Customer
A340: Daniel | B340: Young | C340: Account Wilkins1370 | D340: =TODAY()-584 -> 45453 | E340: Sales Qualified Lead
A341: Elijah | B341: Roberts | C341: Account Ramirez1837 | D341: =TODAY()-584 -> 45453 | E341: Opportunity
A342: Kadence | B342: Martinez | C342: Account Collier276X | D342: =TODAY()-584 -> 45453 | E342: Lead
A343: Coral | B343: Parker | C343: Account Moore962XX | D343: =TODAY()-584 -> 45453 | E343: Customer
A344: Landon | B344: Ward | C344: Account Simpson1 - | D344: =TODAY()-584 -> 45453 | E344: Lead
A345: Aliza | B345: Thompson | C345: Account Barton1670XX - new | D345: =TODAY()-584 -> 45453 | E345: Customer
A346: Kori | B346: Scott | C346: Account Burns308XX - new | D346: =TODAY()-584 -> 45453 | E346: Opportunity
A347: Jax | B347: Wright | C347: Account Release - new | D347: =TODAY()-584 -> 45453 | E347: Product Qualified Lead
A348: Jocelyn | B348: Thompson | C348: Account Olson321 | D348: =TODAY()-584 -> 45453 | E348: Lead
A349: Leilani | B349: Hayes | C349: Account Barber186 | D349: =TODAY()-584 -> 45453 | E349: Customer
... A409: Elaina | B409: Foster | C409: Account Grant1452XX - new | D409: =TODAY()-584 -> 45453 | E409: Customer
A410: Azariah | B410: Wright | C410: Account Johnson1707X - new | D410: =TODAY()-554 -> 45483 | E410: Sales Qualified Lead
A411: Alivia | B411: Perry | C411: Account Medina1876XX - new | D411: =TODAY()-554 -> 45483 | E411: Opportunity
A412: Royal | B412: Hayes | C412: Account Hall1897 - new | D412: =TODAY()-554 -> 45483 | E412: Customer
A413: Jorge | B413: Davis | C413: Account Chandler1281XX - new | D413: =TODAY()-554 -> 45483 | E413: Opportunity
A414: Kaysen | B414: Johnson | C414: Account Abbott1 | D414: =TODAY()-554 -> 45483 | E414: Product Qualified Lead
A415: Keenan | B415: Wright | C415: Account Johnson1707XX | D415: =TODAY()-554 -> 45483 | E415: Product Qualified Lead
A416: Allyson | B416: Campbell | C416: Ramirez & Co. | D416: =TODAY()-554 -> 45483 | E416: Opportunity
A417: John | B417: Foster | C417: Account Bates1455X | D417: =TODAY()-554 -> 45483 | E417: Marketing Qualified Lead
A418: Darian | B418: Sanchez | C418: Account Butler33X | D418: =TODAY()-554 -> 45483 | E418: Customer
A419: Kenna | B419: Martinez | C419: Account Gordon852XX - new - new | D419: =TODAY()-554 -> 45483 | E419: Opportunity
A420: Stella | B420: Butler | C420: Account Stokes814X | D420: =TODAY()-554 -> 45483 | E420: Marketing Qualified Lead
A421: Kayson | B421: Hernandez | C421: Account Brown1230X - new | D421: =TODAY()-554 -> 45483 | E421: Sales Qualified Lead
... A486: Kyndall | B486: Wright | C486: Account Brown1230XX | D486: =TODAY()-554 -> 45483 | E486: Product Qualified Lead
A487: Khloe | B487: Hernandez | C487: Account Adams87XX - new | D487: =TODAY()-523 -> 45514 | E487: Customer
A488: Jonathan | B488: Wright | C488: Account Bennett62XX | D488: =TODAY()-523 -> 45514 | E488: Customer
A489: Kaya | B489: Brooks | C489: Account Phillips1889 - new | D489: =TODAY()-523 -> 45514 | E489: Lead
A490: Isabelle | B490: Wright | C490: Account Alvarez1088 | D490: =TODAY()-523 -> 45514 | E490: Marketing Qualified Lead
A491: Kimberly | B491: Sanders | C491: Account Santiago1975X - new | D491: =TODAY()-523 -> 45514 | E491: Customer
A492: Edgar | B492: Ramirez | C492: Account Smith1859 - new | D492: =TODAY()-523 -> 45514 | E492: Customer
A493: Mariah | B493: Phillips | C493: Account Wise361 | D493: =TODAY()-523 -> 45514 | E493: Customer
A494: Benjamin | B494: Cox | C494: Account Robbins1143XX - new - new | D494: =TODAY()-523 -> 45514 | E494: Product Qualified Lead
...

Sheet ⚡ Events
A1: Activity ID | B1: Subject | C1: Created Date
A2: 10000000067 | B2: Diversity Training Workshop with Sarah | C2: =TODAY()-737 -> 45300
A3: 10000000134 | B3: Sales Team Performance Coaching with Amanda | C3: =TODAY()-737 -> 45300
A4: 10000000653 | B4: Environmental Sustainability Initiatives Review with Michelle | C4: =TODAY()-737 -> 45300
A5: 10000000325 | B5: Supply Chain Efficiency Optimization Meeting with Jennifer | C5: =TODAY()-737 -> 45300
A6: 10000000522 | B6: Leadership Development Program Kickoff with Kevin | C6: =TODAY()-737 -> 45300
A7: 10000000067 | B7: Diversity Training Workshop with Sarah | C7: =TODAY()-737 -> 45300
A8: 10000000353 | B8: Creative Thinking and Problem-Solving Workshop with Lisa | C8: =TODAY()-737 -> 45300
A9: 10000000546 | B9: IT Disaster Recovery Simulation Exercise with Daniel | C9: =TODAY()-737 -> 45300
A10: 10000000689 | B10: Sales Performance Metrics Review with Amanda | C10: =TODAY()-737 -> 45300
A11: 10000000227 | B11: Project Kickoff Meeting with Rachel | C11: =TODAY()-737 -> 45300
A12: 10000000148 | B12: Team Collaboration Enhancement Workshop with Emily | C12: =TODAY()-737 -> 45300
A13: 10000000584 | B13: Customer Engagement Metrics Analysis and Improvement with Mark | C13: =TODAY()-737 -> 45300
... A84: 10000000510 | B84: Supplier Performance Evaluation Meeting with Jennifer | C84: =TODAY()-737 -> 45300
A85: 10000000014 | B85: Employee Feedback Roundtable with Brian | C85: =TODAY()-707 -> 45330
A86: 10000000024 | B86: Marketing Campaign Planning Meeting with David | C86: =TODAY()-707 -> 45330
A87: 10000000297 | B87: Market Research Insights Presentation with Laura | C87: =TODAY()-707 -> 45330
A88: 10000000254 | B88: IT System Integration Planning Session with Daniel | C88: =TODAY()-707 -> 45330
A89: 10000000578 | B89: Team Building and Bonding Activities Implementation with Emily | C89: =TODAY()-707 -> 45330
A90: 10000000595 | B90: Financial Risk Assessment and Mitigation Strategy Session with Chris | C90: =TODAY()-707 -> 45330
A91: 10000000266 | B91: Product Portfolio Review Session with Alex | C91: =TODAY()-707 -> 45330
A92: 10000000026 | B92: Financial Forecast Analysis with Chris | C92: =TODAY()-707 -> 45330
A93: 10000000045 | B93: Leadership Roundtable Discussion with Kevin | C93: =TODAY()-707 -> 45330
A94: 10000000632 | B94: Employee Training and Development Forum with Brian | C94: =TODAY()-707 -> 45330
A95: 10000000545 | B95: Corporate Sustainability Reporting Preparation with Michelle | C95: =TODAY()-707 -> 45330
A96: 10000000316 | B96: IT Infrastructure Security Audit Planning with Daniel | C96: =TODAY()-707 -> 45330
... A170: 10000000208 | B170: Budget Planning Session with Chris | C170: =TODAY()-707 -> 45330
A171: 10000000192 | B171: Quarterly Financial Performance Evaluation and Strategy Adjustment with John | C171: =TODAY()-676 -> 45361
A172: 10000000491 | B172: Project Closure and Lessons Learned Session with Rachel | C172: =TODAY()-676 -> 45361
A173: 10000000258 | B173: Financial Efficiency Improvement Discussion with Chris | C173: =TODAY()-676 -> 45361
A174: 10000000599 | B174: Customer Journey Mapping and Experience Design Workshop with Mark | C174: =TODAY()-676 -> 45361
A175: 10000000384 | B175: Customer Engagement Metrics Analysis and Improvement with Mark | C175: =TODAY()-676 -> 45361
A176: 10000000050 | B176: Marketing Analytics Deep Dive with Laura | C176: =TODAY()-676 -> 45361
A177: 10000000370 | B177: Supplier Relationship Enhancement Strategy Meeting with Jennifer | C177: =TODAY()-676 -> 45361
A178: 10000000512 | B178: Market Expansion Strategy Discussion with Laura | C178: =TODAY()-676 -> 45361
A179: 10000000198 | B179: Innovation Pipeline Management and Prioritization Workshop with Lisa | C179: =TODAY()-676 -> 45361
A180: 10000000424 | B180: Marketing Campaign Planning Meeting with David | C180: =TODAY()-676 -> 45361
A181: 10000000642 | B181: Sales Strategy Alignment Session with Jessica | C181: =TODAY()-676 -> 45361
A182: 10000000056 | B182: Team Performance Metrics Analysis with Emily | C182: =TODAY()-676 -> 45361
... A263: 10000000284 | B263: Inclusive Leadership Training Seminar with Sarah | C263: =TODAY()-676 -> 45361
A264: 10000000026 | B264: Financial Forecast Analysis with Chris | C264: =TODAY()-646 -> 45391
A265: 10000000687 | B265: Annual Shareholder Meeting with John | C265: =TODAY()-646 -> 45391
A266: 10000000437 | B266: IT Security Protocol Review Meeting with Daniel | C266: =TODAY()-646 -> 45391
A267: 10000000406 | B267: Quarterly Performance Analysis Discussion with David | C267: =TODAY()-646 -> 45391
A268: 10000000448 | B268: Supply Chain Resilience Planning with Jennifer | C268: =TODAY()-646 -> 45391
A269: 10000000678 | B269: Creative Problem-Solving Session with Lisa | C269: =TODAY()-646 -> 45391
A270: 10000000103 | B270: Team Conflict Resolution Workshop with Emily | C270: =TODAY()-646 -> 45391
A271: 10000000551 | B271: Agile Project Sprint Planning and Review with Rachel | C271: =TODAY()-646 -> 45391
A272: 10000000138 | B272: Innovation Implementation Strategy Discussion with Lisa | C272: =TODAY()-646 -> 45391
A273: 10000000273 | B273: Project Risk Management Review with David | C273: =TODAY()-646 -> 45391
A274: 10000000507 | B274: Leadership Ethics and Values Discussion with Kevin | C274: =TODAY()-646 -> 45391
A275: 10000000542 | B275: Market Segmentation Analysis Workshop with Laura | C275: =TODAY()-646 -> 45391
... A360: 10000000376 | B360: IT Security Awareness Training and Simulation with Daniel | C360: =TODAY()-646 -> 45391
A361: 10000000239 | B361: Team Building Retreat with Emily | C361: =TODAY()-615 -> 45422
A362: 10000000257 | B362: Sales Training Workshop with Amanda | C362: =TODAY()-615 -> 45422
A363: 10000000059 | B363: Agile Project Management Review with Rachel | C363: =TODAY()-615 -> 45422
A364: 10000000021 | B364: Performance Appraisal Discussion with Emily | C364: =TODAY()-615 -> 45422
A365: 10000000023 | B365: Team Performance Evaluation with Jessica | C365: =TODAY()-615 -> 45422
A366: 10000000291 | B366: Project Closure and Lessons Learned Session with Rachel | C366: =TODAY()-615 -> 45422
A367: 10000000008 | B367: Budget Planning Session with Chris | C367: =TODAY()-615 -> 45422
A368: 10000000670 | B368: Quarterly Sales Strategy Meeting with John | C368: =TODAY()-615 -> 45422
A369: 10000000523 | B369: Ideation Workshop: Generating Innovative Solutions with Lisa | C369: =TODAY()-615 -> 45422
A370: 10000000022 | B370: Stakeholder Engagement Workshop with Michael | C370: =TODAY()-615 -> 45422
A371: 10000000108 | B371: Design Thinking Workshop with Lisa | C371: =TODAY()-615 -> 45422
A372: 10000000575 | B372: Corporate Sustainability Goals Review and Progress Tracking with Michelle | C372: =TODAY()-615 -> 45422
... A460: 10000000376 | B460: IT Security Awareness Training and Simulation with Daniel | C460: =TODAY()-615 -> 45422
A461: 10000000140 | B461: Supplier Risk Management Review with Jennifer | C461: =TODAY()-584 -> 45453
A462: 10000000224 | B462: Marketing Campaign Planning Meeting with David | C462: =TODAY()-584 -> 45453
A463: 10000000405 | B463: Team Building Exercise with Jessica | C463: =TODAY()-584 -> 45453
A464: 10000000433 | B464: Market Trend Analysis Presentation with Laura | C464: =TODAY()-584 -> 45453
A465: 10000000197 | B465: Leadership Development Program Effectiveness Evaluation and Enhancement with Kevin | C465: =TODAY()-584 -> 45453
A466: 10000000685 | B466: Corporate Philanthropy Initiatives Review with Michelle | C466: =TODAY()-584 -> 45453
A467: 10000000618 | B467: Strategic Partnerships Discussion with Daniel | C467: =TODAY()-584 -> 45453
A468: 10000000199 | B468: Customer Journey Mapping and Experience Design Workshop with Mark | C468: =TODAY()-584 -> 45453
A469: 10000000369 | B469: Customer Feedback Integration into Product Development with Mark | C469: =TODAY()-584 -> 45453
A470: 10000000249 | B470: Employee Recognition and Rewards Planning with Brian | C470: =TODAY()-584 -> 45453
A471: 10000000278 | B471: Creative Problem-Solving Session with Lisa | C471: =TODAY()-584 -> 45453
A472: 10000000628 | B472: Leadership Development Workshop with Kevin | C472: =TODAY()-584 -> 45453
... A558: 10000000015 | B558: Market Research Presentation with Laura | C558: =TODAY()-584 -> 45453
A559: 10000000504 | B559: Sales Performance Incentive Planning with Amanda | C559: =TODAY()-554 -> 45483
A560: 10000000115 | B560: Corporate Social Responsibility Impact Assessment with Michelle | C560: =TODAY()-554 -> 45483
A561: 10000000278 | B561: Creative Problem-Solving Session with Lisa | C561: =TODAY()-554 -> 45483
A562: 10000000456 | B562: Team Performance Metrics Analysis with Emily | C562: =TODAY()-554 -> 45483
A563: 10000000427 | B563: Project Kickoff Meeting with Rachel | C563: =TODAY()-554 -> 45483
A564: 10000000455 | B564: Quarterly Business Review Meeting with John | C564: =TODAY()-554 -> 45483
A565: 10000000477 | B565: Leadership Succession Planning Forum with Kevin | C565: =TODAY()-554 -> 45483
A566: 10000000015 | B566: Market Research Presentation with Laura | C566: =TODAY()-554 -> 45483
A567: 10000000099 | B567: Diversity and Inclusion Awareness Workshop with Sarah | C567: =TODAY()-554 -> 45483
A568: 10000000349 | B568: Sales Strategy Execution Review with Amanda | C568: =TODAY()-554 -> 45483
A569: 10000000695 | B569: Inventory Management Optimization Meeting with Jennifer | C569: =TODAY()-554 -> 45483
A570: 10000000527 | B570: Market Disruption Analysis Discussion with Laura | C570: =TODAY()-554 -> 45483
... A662: 10000000387 | B662: Market Segmentation Strategy Refinement Workshop with Laura | C662: =TODAY()-554 -> 45483
A663: 10000000306 | B663: Agile Development Process Improvement Session with Rachel | C663: =TODAY()-523 -> 45514
A664: 10000000629 | B664: Ideation and Innovation Session with Lisa | C664: =TODAY()-523 -> 45514
A665: 10000000023 | B665: Team Performance Evaluation with Jessica | C665: =TODAY()-523 -> 45514
A666: 10000000078 | B666: Creative Problem-Solving Session with Lisa | C666: =TODAY()-523 -> 45514
A667: 10000000355 | B667: Supply Chain Resilience Assessment and Planning with Jennifer | C667: =TODAY()-523 -> 45514
A668: 10000000408 | B668: Budget Planning Session with Chris | C668: =TODAY()-523 -> 45514
A669: 10000000613 | B669: Supply Chain Optimization Meeting with Jennifer | C669: =TODAY()-523 -> 45514
A670: 10000000181 | B670: Agile Sprint Planning and Execution Review with Rachel | C670: =TODAY()-523 -> 45514
...

Sheet ⚡ Opportunities
A1: Opportunity ID | B1: Name | C1: Created Date | D1: Close Date | E1: Stage | F1: Closed | G1: Won | H1: Amount
A2: 0064T000008ygriQAA | B2: Opportunity for Blair183 | C2: =TODAY()-737 -> 45300 | D2: =TODAY()-722 -> 45315 | E2: Closed Won | F2: TRUE | G2: TRUE | H2: 1650
A3: 0064T000008yguZQAQ | B3: Opportunity for Leonard584X - new | C3: =TODAY()-737 -> 45300 | D3: =TODAY()-727 -> 45310 | E3: Closed Lost | F3: TRUE | G3: FALSE | H3: 2170
A4: 0064T000008yguMQAQ | B4: Opportunity for Brown1230XX - new | C4: =TODAY()-737 -> 45300 | D4: =TODAY()-726 -> 45311 | E4: Closed Won | F4: TRUE | G4: TRUE | H4: 2110
A5: 0064T000008yguyQAA | B5: Opportunity for Swanson1068X | C5: =TODAY()-737 -> 45300 | E5: Prospecting | F5: FALSE | G5: FALSE | H5: 240
A6: 0064T000002kJaHQAU | B6: Opportunity for McCormick23 - new | C6: =TODAY()-737 -> 45300 | D6: =TODAY()-719 -> 45318 | E6: Closed Won | F6: TRUE | G6: TRUE | H6: 130
A7: 0064T000002kJbPQAU | B7: Opportunity for Hardy1507XX - new | C7: =TODAY()-737 -> 45300 | D7: =TODAY()-725 -> 45312 | E7: Closed Won | F7: TRUE | G7: TRUE | H7: 1280
A8: 0064T000008ygubQAA | B8: Opportunity for Brown1230XX | C8: =TODAY()-737 -> 45300 | D8: =TODAY()-719 -> 45318 | E8: Closed Won | F8: TRUE | G8: TRUE | H8: 1580
A9: 0064T000008ygstQAA | B9: Opportunity for Santiago1975X - new | C9: =TODAY()-737 -> 45300 | D9: =TODAY()-707 -> 45330 | E9: Closed Won | F9: TRUE | G9: TRUE | H9: 1310
A10: 0064T000002kJYFQA2 | B10: Opportunity for Armstrong600 - new | C10: =TODAY()-737 -> 45300 | D10: =TODAY()-727 -> 45310 | E10: Closed Won | F10: TRUE | G10: TRUE | H10: 2270
A11: 0064T000008ygrWQAQ | B11: Opportunity for Todd1938 | C11: =TODAY()-737 -> 45300 | E11: Prospecting | F11: FALSE | G11: FALSE | H11: 2500
A12: 0064T000008ygrgQAA | B12: Opportunity for Flowers1427X | C12: =TODAY()-737 -> 45300 | D12: =TODAY()-717 -> 45320 | E12: Closed Won | F12: TRUE | G12: TRUE | H12: 2330
A13: 0064T000008ygvkQAA | B13: Opportunity for Abbott1184XX | C13: =TODAY()-737 -> 45300 | D13: =TODAY()-726 -> 45311 | E13: Closed Lost | F13: TRUE | G13: FALSE | H13: 640
A14: 0064T000008ygrvQAA | B14: Opportunity for Butler33X - new | C14: =TODAY()-737 -> 45300 | D14: =TODAY()-721 -> 45316 | E14: Closed Won | F14: TRUE | G14: TRUE | H14: 6360
A15: 0064T000008ygq0QAA | B15: Opportunity for Moss1820XX | C15: =TODAY()-737 -> 45300 | D15: =TODAY()-718 -> 45319 | E15: Closed Lost | F15: TRUE | G15: FALSE | H15: 1490
A16: 0064T000008ygvVQAQ | B16: Opportunity for Carol | C16: =TODAY()-737 -> 45300 | D16: =TODAY()-718 -> 45319 | E16: Closed Won | F16: TRUE | G16: TRUE | H16: 800
A17: 0064T000008ygspQAA | B17: Opportunity for Rodriquez958X - new | C17: =TODAY()-737 -> 45300 | E17: Prospecting | F17: FALSE | G17: FALSE | H17: 1510
A18: 0064T000008ygvqQAA | B18: Opportunity for Daniels627XX - new | C18: =TODAY()-737 -> 45300 | D18: =TODAY()-719 -> 45318 | E18: Closed Lost | F18: TRUE | G18: FALSE | H18: 310
A19: 0064T000002kJYgQAM | B19: Opportunity for Todd162X - new | C19: =TODAY()-737 -> 45300 | D19: =TODAY()-720 -> 45317 | E19: Closed Won | F19: TRUE | G19: TRUE | H19: 1210
A20: 0064T000008ygrvQAA | B20: Opportunity for Butler33X - new | C20: =TODAY()-737 -> 45300 | D20: =TODAY()-716 -> 45321 | E20: Closed Won | F20: TRUE | G20: TRUE | H20: 6360
A21: 0064T000008yguGQAQ | B21: Opportunity for Olson321X - new | C21: =TODAY()-737 -> 45300 | D21: =TODAY()-713 -> 45324 | E21: Closed Won | F21: TRUE | G21: TRUE | H21: 820
A22: 0064T000008ygtgQAA | B22: Opportunity for Bennett62XX | C22: =TODAY()-737 -> 45300 | E22: Perception Analysis | F22: FALSE | G22: FALSE | H22: 1450
A23: 0064T000008yguSQAQ | B23: Opportunity for McCormick23X - new | C23: =TODAY()-737 -> 45300 | D23: =TODAY()-710 -> 45327 | E23: Closed Won | F23: TRUE | G23: TRUE | H23: 760
A24: 0064T000008ygupQAA | B24: Opportunity for Phelps205 | C24: =TODAY()-737 -> 45300 | D24: =TODAY()-708 -> 45329 | E24: Closed Lost | F24: TRUE | G24: FALSE | H24: 1320
A25: 0064T000008ygvyQAA | B25: Opportunity for Klein1486XXX - new | C25: =TODAY()-737 -> 45300 | E25: Proposal/Price Quote | F25: FALSE | G25: FALSE | H25: 740
A26: 0064T000008ygvVQAQ | B26: Opportunity for Nguyen1971XX - new | C26: =TODAY()-737 -> 45300 | D26: =TODAY()-724 -> 45313 | E26: Closed Won | F26: TRUE | G26: TRUE | H26: 2060
A27: 0064T000008yguPQAQ | B27: Opportunity for Murphy1963 - new | C27: =TODAY()-737 -> 45300 | D27: =TODAY()-707 -> 45330 | E27: Closed Won | F27: TRUE | G27: TRUE | H27: 640
A28: 0064T000008ygvEQAQ | B28: Opportunity for Barker1602XX - new | C28: =TODAY()-737 -> 45300 | D28: =TODAY()-717 -> 45320 | E28: Closed Won | F28: TRUE | G28: TRUE | H28: 2430
A29: 0064T000008ygt4QAA | B29: Opportunity for Todd162XX | C29: =TODAY()-737 -> 45300 | D29: =TODAY()-727 -> 45310 | E29: Closed Won | F29: TRUE | G29: TRUE | H29: 730
A30: 0064T000008ygwMQAQ | B30: Opportunity for Robbins1143XX | C30: =TODAY()-737 -> 45300 | D30: =TODAY()-723 -> 45314 | E30: Closed Won | F30: TRUE | G30: TRUE | H30: 390
A31: 0064T000008ygsSQAQ | B31: Opportunity for Andrews1792 | C31: =TODAY()-737 -> 45300 | D31: =TODAY()-709 -> 45328 | E31: Closed Lost | F31: TRUE | G31: FALSE | H31: 850
A32: 0064T000008ygtFQAQ | B32: Opportunity for Robbins1143X | C32: =TODAY()-737 -> 45300 | D32: =TODAY()-708 -> 45329 | E32: Closed Lost | F32: TRUE | G32: FALSE | H32: 1740
A33: 0064T000008ygvWQAQ | B33: Opportunity for Alvarez1088XXX | C33: =TODAY()-737 -> 45300 | D33: =TODAY()-724 -> 45313 | E33: Closed Lost | F33: TRUE | G33: FALSE | H33: 580
A34: 0064T000002kJXdQAM | B34: Opportunity for Banks821XX - new | C34: =TODAY()-737 -> 45300 | D34: =TODAY()-712 -> 45325 | E34: Closed Lost | F34: TRUE | G34: FALSE | H34: 890
A35: 0064T000008ygsAQAQ | B35: Opportunity for Joseph722 - new | C35: =TODAY()-737 -> 45300 | E35: Prospecting | F35: FALSE | G35: FALSE | H35: 1170
A36: 0064T000008ygspQAA | B36: Opportunity for Rodriquez958X - new | C36: =TODAY()-737 -> 45300 | E36: Prospecting | F36: FALSE | G36: FALSE | H36: 1510
A37: 0064T000008ygutQAA | B37: Opportunity for Olson321 - new | C37: =TODAY()-737 -> 45300 | D37: =TODAY()-720 -> 45317 | E37: Closed Won | F37: TRUE | G37: TRUE | H37: 1110
A38: 0064T000008yguwQAA | B38: Opportunity for Wilkins1370XX - new | C38: =TODAY()-737 -> 45300 | E38: Negotiation/Review | F38: FALSE | G38: FALSE | H38: 1040
A39: 0064T000008ygspQAA | B39: Opportunity for Moore962X | C39: =TODAY()-737 -> 45300 | E39: Qualification | F39: FALSE | G39: FALSE | H39: 740
A40: 0064T000008ygtJQAQ | B40: Opportunity for Chandler1816XX - new | C40: =TODAY()-737 -> 45300 | D40: =TODAY()-723 -> 45314 | E40: Closed Lost | F40: TRUE | G40: FALSE | H40: 150
A41: 0064T000002kJYxQAM | B41: Opportunity for Olson321XX - new | C41: =TODAY()-737 -> 45300 | E41: Needs Analysis | F41: FALSE | G41: FALSE | H41: 1870
A42: 0064T000008ygulQAA | B42: Opportunity for Conner5X | C42: =TODAY()-737 -> 45300 | D42: =TODAY()-717 -> 45320 | E42: Closed Won | F42: TRUE | G42: TRUE | H42: 260
A43: 0064T000002kJSnQAM | B43: Opportunity for Johnson1707XX - new | C43: =TODAY()-737 -> 45300 | D43: =TODAY()-712 -> 45325 | E43: Closed Won | F43: TRUE | G43: TRUE | H43: 2180
A44: 0064T000008ygrnQAA | B44: Upsell Deal | C44: =TODAY()-737 -> 45300 | D44: =TODAY()-711 -> 45326 | E44: Closed Won | F44: TRUE | G44: TRUE | H44: 390
A45: 0064T000008ygwGQAQ | B45: Opportunity for Robbins1143X - new | C45: =TODAY()-737 -> 45300 | D45: =TODAY()-714 -> 45323 | E45: Closed Lost | F45: TRUE | G45: FALSE | H45: 780
A46: 0064T000008ygu7QAA | B46: Opportunity for Allison281XX | C46: =TODAY()-737 -> 45300 | D46: =TODAY()-709 -> 45328 | E46: Closed Lost | F46: TRUE | G46: FALSE | H46: 410
A47: 0064T000008yguyQAA | B47: Opportunity for Swanson1068X | C47: =TODAY()-737 -> 45300 | E47: Prospecting | F47: FALSE | G47: FALSE | H47: 240
A48: 0064T000008ygswQAA | B48: Opportunity for Armstrong600X - new | C48: =TODAY()-737 -> 45300 | D48: =TODAY()-722 -> 45315 | E48: Closed Won | F48: TRUE | G48: TRUE | H48: 1450
A49: 0064T000002kJXbQAM | B49: Opportunity for Simpson1385XXX - new | C49: =TODAY()-737 -> 45300 | D49: =TODAY()-720 -> 45317 | E49: Closed Won | F49: TRUE | G49: TRUE | H49: 1420
A50: 0064T000008ygsjQAA | B50: Opportunity for Alvarez - new | C50: =TODAY()-737 -> 45300 | D50: =TODAY()-710 -> 45327 | E50: Closed Won | F50: TRUE | G50: TRUE | H50: 3030
A51: 0064T000008ygvGQAQ | B51: Opportunity for Todd162XXX | C51: =TODAY()-737 -> 45300 | D51: =TODAY()-724 -> 45313 | E51: Closed Won | F51: TRUE | G51: TRUE | H51: 1840
A52: 0064T000008ygv1QAA | B52: Opportunity for Brown1230 | C52: =TODAY()-737 -> 45300 | D52: =TODAY()-721 -> 45316 | E52: Closed Lost | F52: TRUE | G52: FALSE | H52: 820
A53: 0064T000008ygrtQAA | B53: Opportunity for Wilkins1370 - new | C53: =TODAY()-737 -> 45300 | D53: =TODAY()-712 -> 45325 | E53: Closed Won | F53: TRUE | G53: TRUE | H53: 1540
A54: 0064T000008ygrdQAA | B54: Opportunity for Christensen684X | C54: =TODAY()-737 -> 45300 | D54: =TODAY()-715 -> 45322 | E54: Closed Won | F54: TRUE | G54: TRUE | H54: 2250
A55: 0064T000008ygszQAA | B55: Opportunity for Dennis956XXX - new | C55: =TODAY()-737 -> 45300 | D55: =TODAY()-718 -> 45319 | E55: Closed Won | F55: TRUE | G55: TRUE | H55: 120
A56: 0064T000008ygqFQAQ | B56: Customer Renewal | C56: =TODAY()-737 -> 45300 | D56: =TODAY()-720 -> 45317 | E56: Closed Won | F56: TRUE | G56: TRUE | H56: 560
A57: 0064T000008ygvKQAQ | B57: Opportunity for Rice1187X | C57: =TODAY()-737 -> 45300 | D57: =TODAY()-723 -> 45314 | E57: Closed Won | F57: TRUE | G57: TRUE | H57: 2440
A58: 0064T000008ygtVQAQ | B58: Opportunity for Barker1602 | C58: =TODAY()-737 -> 45300 | D58: =TODAY()-725 -> 45312 | E58: Closed Won | F58: TRUE | G58: TRUE | H58: 2460
A59: 0064T000008yguIQAQ | B59: Opportunity for Gordon852 - new | C59: =TODAY()-737 -> 45300 | D59: =TODAY()-716 -> 45321 | E59: Closed Lost | F59: TRUE | G59: FALSE | H59: 1670
A60: 0064T000008ygucQAA | B60: Opportunity for Christensen684X - new | C60: =TODAY()-737 -> 45300 | D60: =TODAY()-721 -> 45316 | E60: Closed Won | F60: TRUE | G60: TRUE | H60: 560
A61: 0064T000008ygtNQAQ | B61: Opportunity for Elliott511XX - new | C61: =TODAY()-737 -> 45300 | E61: Proposal/Price Quote | F61: FALSE | G61: FALSE | H61: 950
A62: 0064T000008ygtnQAA | B62: Opportunity for Alvarez1088XX | C62: =TODAY()-737 -> 45300 | D62: =TODAY()-727 -> 45310 | E62: Closed Won | F62: TRUE | G62: TRUE | H62: 800
A63: 0064T000008ygsPQAQ | B63: Opportunity for Lyons | C63: =TODAY()-737 -> 45300 | D63: =TODAY()-716 -> 45321 | E63: Closed Won | F63: TRUE | G63: TRUE | H63: 2330
A64: 0064T000002kJWaQAM | B64: Opportunity for Leonard584XX - new | C64: =TODAY()-737 -> 45300 | D64: =TODAY()-726 -> 45311 | E64: Closed Lost | F64: TRUE | G64: FALSE | H64: 2260
A65: 0064T000008ygsiQAA | B65: Opportunity for Burton1994X - new | C65: =TODAY()-737 -> 45300 | D65: =TODAY()-717 -> 45320 | E65: Closed Won | F65: TRUE | G65: TRUE | H65: 2340
A66: 0064T000002kJYJQA2 | B66: Opportunity for Stokes814X - new | C66: =TODAY()-737 -> 45300 | D66: =TODAY()-712 -> 45325 | E66: Closed Won | F66: TRUE | G66: TRUE | H66: 1200
A67: 0064T000008ygrSQAQ | B67: Opportunity for Frazier196XX | C67: =TODAY()-737 -> 45300 | D67: =TODAY()-718 -> 45319 | E67: Closed Won | F67: TRUE | G67: TRUE | H67: 360
A68: 0064T000002kJX3QAM | B68: Opportunity for Ramirez1837X - new | C68: =TODAY()-737 -> 45300 | D68: =TODAY()-710 -> 45327 | E68: Closed Lost | F68: TRUE | G68: FALSE | H68: 2060
A69: 0064T000008yguRQAQ | B69: Opportunity for Hart387X - new | C69: =TODAY()-737 -> 45300 | D69: =TODAY()-710 -> 45327 | E69: Closed Won | F69: TRUE | G69: TRUE | H69: 4090
A70: 0064T000008ygsJQAQ | B70: Opportunity for Estrada957X | C70: =TODAY()-737 -> 45300 | D70: =TODAY()-725 -> 45312 | E70: Closed Won | F70: TRUE | G70: TRUE | H70: 2000
A71: 0064T000008ygvSQAQ | B71: Opportunity for Moss1820X - new | C71: =TODAY()-737 -> 45300 | D71: =TODAY()-716 -> 45321 | E71: Closed Lost | F71: TRUE | G71: FALSE | H71: 1140
A72: 0064T000002kJZXQA2 | B72: Opportunity for Abbott11 - new | C72: =TODAY()-737 -> 45300 | E72: Negotiation/Review | F72: FALSE | G72: FALSE | H72: 250
A73: 0064T000002kJaiQAE | B73: Opportunity for Frazier196 - new | C73: =TODAY()-737 -> 45300 | D73: =TODAY()-716 -> 45321 | E73: Closed Won | F73: TRUE | G73: TRUE | H73: 1220
A74: 0064T000008ygrhQAA | B74: Opportunity for Nguyen1971X | C74: =TODAY()-737 -> 45300 | E74: Proposal/Price Quote | F74: FALSE | G74: FALSE | H74: 550
A75: 0064T000008ygwIQAQ | B75: Opportunity for Phillips1889XX | C75: =TODAY()-737 -> 45300 | D75: =TODAY()-713 -> 45324 | E75: Closed Lost | F75: TRUE | G75: FALSE | H75: 640
A76: 0064T000008ygvRQAQ | B76: Opportunity for Robbins1143 | C76: =TODAY()-707 -> 45330 | D76: =TODAY()-685 -> 45352 | E76: Closed Won | F76: TRUE | G76: TRUE | H76: 2190
A77: 0064T000008ygvBQAQ | B77: Opportunity for Grant1452XX - new | C77: =TODAY()-707 -> 45330 | D77: =TODAY()-697 -> 45340 | E77: Closed Won | F77: TRUE | G77: TRUE | H77: 1020
A78: 0064T000002kJcdQAE | B78: Opportunity for Stokes949XX - new | C78: =TODAY()-707 -> 45330 | D78: =TODAY()-694 -> 45343 | E78: Closed Won | F78: TRUE | G78: TRUE | H78: 1570
A79: 0064T000008ygu3QAA | B79: Opportunity for Christensen684XX | C79: =TODAY()-707 -> 45330 | D79: =TODAY()-685 -> 45352 | E79: Closed Won | F79: TRUE | G79: TRUE | H79: 1840
A80: 0064T000008yguIQAQ | B80: Opportunity for Collier5 | C80: =TODAY()-707 -> 45330 | E80: Negotiation/Review | F80: FALSE | G80: FALSE | H80: 130
A81: 0064T000002kJVLQA2 | B81: Opportunity for Wilkerson900 - new | C81: =TODAY()-707 -> 45330 | D81: =TODAY()-691 -> 45346 | E81: Closed Won | F81: TRUE | G81: TRUE | H81: 340
A82: 0064T000008ygrlQAA | B82: Opportunity for Klein1 - new | C82: =TODAY()-707 -> 45330 | D82: =TODAY()-695 -> 45342 | E82: Closed Lost | F82: TRUE | G82: FALSE | H82: 2330
A83: 0064T000008ygrbQAA | B83: Opportunity for Chandler1816X | C83: =TODAY()-707 -> 45330 | E83: Prospecting | F83: FALSE | G83: FALSE | H83: 2470
A84: 0064T000008yguzQAA | B84: Opportunity for Baker1304 | C84: =TODAY()-707 -> 45330 | E84: Qualification | F84: FALSE | G84: FALSE | H84: 200
A85: 0064T000002kJaDQAU | B85: Opportunity for Lyons494XX - new | C85: =TODAY()-707 -> 45330 | D85: =TODAY()-692 -> 45345 | E85: Closed Lost | F85: TRUE | G85: FALSE | H85: 1690
A86: 0064T000008ygu5QAA | B86: Opportunity for Barton1764X | C86: =TODAY()-707 -> 45330 | D86: =TODAY()-694 -> 45343 | E86: Closed Lost | F86: TRUE | G86: FALSE | H86: 1600
A87: 0064T000008ygvXQAQ | B87: Opportunity for Johnson | C87: =TODAY()-707 -> 45330 | D87: =TODAY()-679 -> 45358 | E87: Closed Won | F87: TRUE | G87: TRUE | H87: 650
A88: 0064T000008ygueQAA | B88: Opportunity for Butler582XX | C88: =TODAY()-707 -> 45330 | D88: =TODAY()-688 -> 45349 | E88: Closed Won | F88: TRUE | G88: TRUE | H88: 190
A89: 0064T000008yguNQAQ | B89: New 2021 Deal | C89: =TODAY()-707 -> 45330 | E89: Prospecting | F89: FALSE | G89: FALSE | H89: 2470
A90: 0064T000008ygspQAA | B90: Opportunity for Moore962X | C90: =TODAY()-707 -> 45330 | E90: Qualification | F90: FALSE | G90: FALSE | H90: 740
A91: 0064T000008yguSQAQ | B91: Opportunity for Leonard584XX | C91: =TODAY()-707 -> 45330 | D91: =TODAY()-678 -> 45359 | E91: Closed Lost | F91: TRUE | G91: FALSE | H91: 1940
A92: 0064T000008ygtoQAA | B92: Opportunity for Cunningham662X - new | C92: =TODAY()-707 -> 45330 | D92: =TODAY()-692 -> 45345 | E92: Closed Lost | F92: TRUE | G92: FALSE | H92: 410
A93: 0064T000008ygrkQAA | B93: Opportunity for Watson1794X | C93: =TODAY()-707 -> 45330 | D93: =TODAY()-687 -> 45350 | E93: Closed Won | F93: TRUE | G93: TRUE | H93: 200
A94: 0064T000002kJTxQAM | B94: Opportunity for Barton1670XX - new | C94: =TODAY()-707 -> 45330 | D94: =TODAY()-693 -> 45344 | E94: Closed Lost | F94: TRUE | G94: FALSE | H94: 510
A95: 0064T000008ygtYQAQ | B95: Opportunity for Stokes | C95: =TODAY()-707 -> 45330 | D95: =TODAY()-685 -> 45352 | E95: Closed Won | F95: TRUE | G95: TRUE | H95: 150
A96: 0064T000008ygtVQAQ | B96: Opportunity for Barker1602 | C96: =TODAY()-707 -> 45330 | D96: =TODAY()-678 -> 45359 | E96: Closed Won | F96: TRUE | G96: TRUE | H96: 2460
A97: 0064T000008ygw2QAA | B97: Opportunity for Allison281XX - new | C97: =TODAY()-707 -> 45330 | D97: =TODAY()-695 -> 45342 | E97: Closed Won | F97: TRUE | G97: TRUE | H97: 4300
A98: 0064T000008ygwLQAQ | B98: Opportunity for Elliott511X - new | C98: =TODAY()-707 -> 45330 | E98: Proposal/Price Quote | F98: FALSE | G98: FALSE | H98: 1440
A99: 0064T000008ygtOQAQ | B99: Opportunity for Hart387XX | C99: =TODAY()-707 -> 45330 | D99: =TODAY()-694 -> 45343 | E99: Closed Won | F99: TRUE | G99: TRUE | H99: 1330
A100: 0064T000002kJcdQAE | B100: Opportunity for Stokes949XX - new | C100: =TODAY()-707 -> 45330 | D100: =TODAY()-683 -> 45354 | E100: Closed Won | F100: TRUE | G100: TRUE | H100: 1570
...

Sheet 📊 12-Month Sales Forecast Dash
AA1: Linear Regression | AH1: Moving Average | AO1: Simple Exponential Smoothing
R2: Month Year | S2: Acquired Leads | T2: Meetings Booked | U2: New Opportunities | V2: # Projected Closed/Won | W2: $ Forecasted Revenue | X2: Total Revenue | Y2: Label | AA2: Month Year | AB2: Acquired Leads | AC2: Meetings Booked | AD2: New Opportunities | AE2: Closed/Won | AF2: New Revenue per Month | AH2: Month Year | AI2: Acquired Leads | AJ2: Meetings Booked | AK2: New Opportunities | AL2: Closed/Won | AM2: New Revenue per Month | AO2: Month Year | AP2: Acquired Leads | AQ2: Meetings Booked | AR2: New Opportunities | AS2: Closed/Won | AT2: New Revenue per Month | AU2: =AA1 -> Linear Regression
B3: Salesforce 12-Month Sales Forecast Dashboard | R3: =D14 -> 46023 | S3: {=IF(C6=AA1,AB27:AF50,IF(C6=AH1,AI27:AM50,IF(C6=AO1,AP27:AT50,)))} -> 88.979183 | T3: 118.47633 | U3: 110.40166 | V3: 61.237095 | W3: 99793.517 | X3: {=_xlfn.SCAN(0, W3:W26, _xlfn.LAMBDA(_xlpm.x,_xlpm.y, _xlpm.x + _xlpm.y))} -> 99793.517 | Y3: {=_xlfn.BYROW(W3:W26, _xlfn.LAMBDA(_xlpm.x, IF(_xlpm.x = "", "", "$" & TEXT(_xlpm.x, IF(_xlpm.x >= 1000000, "#,###,,", IF(_xlpm.x >= 1000, "#,###,", "#,###")) ) & IF(_xlpm.x >= 1000000, "M", IF(_xlpm.x >= 1000, "k", "")) ) ))} -> $100k | AA3: =EDATE(AA4,-1) -> 45292 | AB3: =COUNTIFS('⚡ Leads'!D:D,">="&AA3,'⚡ Leads'!D:D,"<"&EDATE(AA3,1)) -> 60 | AC3: =COUNTIFS('⚡ Events'!C:C,">="&AA3,'⚡ Events'!C:C,"<"&EDATE(AA3,1)) -> 83 | AD3: =COUNTIFS('⚡ Opportunities'!C:C,">="&AA3,'⚡ Opportunities'!C:C,"<"&EDATE(AA3,1)) -> 74 | AE3: =COUNTIFS('⚡ Opportunities'!C:C,">="&AA3,'⚡ Opportunities'!C:C,"<"&EDATE(AA3,1),'⚡ Opportunities'!F:F,TRUE,'⚡ Opportunities'!G:G,TRUE) -> 42 | AF3: =SUMIFS('⚡ Opportunities'!H:H,'⚡ Opportunities'!C:C,">="&AA3,'⚡ Opportunities'!C:C,"<"&EDATE(AA3,1),'⚡ Opportunities'!F:F,TRUE,'⚡ Opportunities'!G:G,TRUE) -> 71170 | AH3: =EDATE(AH4,-1) -> 45292 | AI3: =COUNTIFS('⚡ Leads'!D:D,">="&AA3,'⚡ Leads'!D:D,"<"&EDATE(AA3,1)) -> 60 | AJ3: =COUNTIFS('⚡ Events'!C:C,">="&AA3,'⚡ Events'!C:C,"<"&EDATE(AA3,1)) -> 83 | AK3: =COUNTIFS('⚡ Opportunities'!C:C,">="&AA3,'⚡ Opportunities'!C:C,"<"&EDATE(AA3,1)) -> 74 | AL3: =COUNTIFS('⚡ Opportunities'!C:C,">="&AA3,'⚡ Opportunities'!C:C,"<"&EDATE(AA3,1),'⚡ Opportunities'!F:F,TRUE,'⚡ Opportunities'!G:G,TRUE) -> 42 | AM3: =SUMIFS('⚡ Opportunities'!H:H,'⚡ Opportunities'!C:C,">="&AA3,'⚡ Opportunities'!C:C,"<"&EDATE(AA3,1),'⚡ Opportunities'!F:F,TRUE,'⚡ Opportunities'!G:G,TRUE) -> 71170 | AO3: =EDATE(AO4,-1) -> 45231 | AP3: =COUNTIFS('⚡ Leads'!D:D,">="&AA3,'⚡ Leads'!D:D,"<"&EDATE(AA3,1)) -> 60 | AQ3: =COUNTIFS('⚡ Events'!C:C,">="&AA3,'⚡ Events'!C:C,"<"&EDATE(AA3,1)) -> 83 | AR3: =COUNTIFS('⚡ Opportunities'!C:C,">="&AA3,'⚡ Opportunities'!C:C,"<"&EDATE(AA3,1)) -> 74 | AS3: =COUNTIFS('⚡ Opportunities'!C:C,">="&AA3,'⚡ Opportunities'!C:C,"<"&EDATE(AA3,1),'⚡ Opportunities'!F:F,TRUE,'⚡ Opportunities'!G:G,TRUE) -> 42 | AT3: =SUMIFS('⚡ Opportunities'!H:H,'⚡ Opportunities'!C:C,">="&AA3,'⚡ Opportunities'!C:C,"<"&EDATE(AA3,1),'⚡ Opportunities'!F:F,TRUE,'⚡ Opportunities'!G:G,TRUE) -> 71170 | AU3: =AH1 -> Moving Average
R4: {=IFERROR(_xlfn.BYROW(_xlfn.SEQUENCE(23),_xlfn.LAMBDA(_xlpm.x,IFERROR(DATE(YEAR(R3),MONTH(R3)+_xlpm.x,1),"Month "&(_xlpm.x+1)))),"")} -> 46054 | S4: 89.149743 | T4: 118.71602 | U4: 110.60535 | V4: 61.192974 | W4: 99950.892 | X4: 199744.41 | Y4: $100k | AA4: =EDATE(AA5,-1) -> 45323 | AB4: =COUNTIFS('⚡ Leads'!D:D,">="&AA4,'⚡ Leads'!D:D,"<"&EDATE(AA4,1)) -> 63 | AC4: =COUNTIFS('⚡ Events'!C:C,">="&AA4,'⚡ Events'!C:C,"<"&EDATE(AA4,1)) -> 86 | AD4: =COUNTIFS('⚡ Opportunities'!C:C,">="&AA4,'⚡ Opportunities'!C:C,"<"&EDATE(AA4,1)) -> 80 | AE4: =COUNTIFS('⚡ Opportunities'!C:C,">="&AA4,'⚡ Opportunities'!C:C,"<"&EDATE(AA4,1),'⚡ Opportunities'!F:F,TRUE,'⚡ Opportunities'!G:G,TRUE) -> 40 | AF4: =SUMIFS('⚡ Opportunities'!H:H,'⚡ Opportunities'!C:C,">="&AA4,'⚡ Opportunities'!C:C,"<"&EDATE(AA4,1),'⚡ Opportunities'!F:F,TRUE,'⚡ Opportunities'!G:G,TRUE) -> 70960 | AH4: =EDATE(AH5,-1) -> 45323 | AI4: =COUNTIFS('⚡ Leads'!D:D,">="&AA4,'⚡ Leads'!D:D,"<"&EDATE(AA4,1)) -> 63 | AJ4: =COUNTIFS('⚡ Events'!C:C,">="&AA4,'⚡ Events'!C:C,"<"&EDATE(AA4,1)) -> 86 | AK4: =COUNTIFS('⚡ Opportunities'!C:C,">="&AA4,'⚡ Opportunities'!C:C,"<"&EDATE(AA4,1)) -> 80 | AL4: =COUNTIFS('⚡ Opportunities'!C:C,">="&AA4,'⚡ Opportunities'!C:C,"<"&EDATE(AA4,1),'⚡ Opportunities'!F:F,TRUE,'⚡ Opportunities'!G:G,TRUE) -> 40 | AM4: =SUMIFS('⚡ Opportunities'!H:H,'⚡ Opportunities'!C:C,">="&AA4,'⚡ Opportunities'!C:C,"<"&EDATE(AA4,1),'⚡ Opportunities'!F:F,TRUE,'⚡ Opportunities'!G:G,TRUE) -> 70960 | AO4: =EDATE(AO5,-1) -> 45261 | AP4: =COUNTIFS('⚡ Leads'!D:D,">="&AA4,'⚡ Leads'!D:D,"<"&EDATE(AA4,1)) -> 63 | AQ4: =COUNTIFS('⚡ Events'!C:C,">="&AA4,'⚡ Events'!C:C,"<"&EDATE(AA4,1)) -> 86 | AR4: =COUNTIFS('⚡ Opportunities'!C:C,">="&AA4,'⚡ Opportunities'!C:C,"<"&EDATE(AA4,1)) -> 80 | AS4: =COUNTIFS('⚡ Opportunities'!C:C,">="&AA4,'⚡ Opportunities'!C:C,"<"&EDATE(AA4,1),'⚡ Opportunities'!F:F,TRUE,'⚡ Opportunities'!G:G,TRUE) -> 40 | AT4: =SUMIFS('⚡ Opportunities'!H:H,'⚡ Opportunities'!C:C,">="&AA4,'⚡ Opportunities'!C:C,"<"&EDATE(AA4,1),'⚡ Opportunities'!F:F,TRUE,'⚡ Opportunities'!G:G,TRUE) -> 70960 | AU4: =AO1 -> Simple Exponential Smoothing
R5: 46082 | S5: 89.417364 | T5: 119.05736 | U5: 110.9519 | V5: 61.183476 | W5: 99972.213 | X5: 299716.62 | Y5: $100k | AA5: =EDATE(AA6,-1) -> 45352 | AB5: =COUNTIFS('⚡ Leads'!D:D,">="&AA5,'⚡ Leads'!D:D,"<"&EDATE(AA5,1)) -> 67 | AC5: =COUNTIFS('⚡ Events'!C:C,">="&AA5,'⚡ Events'!C:C,"<"&EDATE(AA5,1)) -> 93 | AD5: =COUNTIFS('⚡ Opportunities'!C:C,">="&AA5,'⚡ Opportunities'!C:C,"<"&EDATE(AA5,1)) -> 84 | AE5: =COUNTIFS('⚡ Opportunities'!C:C,">="&AA5,'⚡ Opportunities'!C:C,"<"&EDATE(AA5,1),'⚡ Opportunities'!F:F,TRUE,'⚡ Opportunities'!G:G,TRUE) -> 44 | AF5: =SUMIFS('⚡ Opportunities'!H:H,'⚡ Opportunities'!C:C,">="&AA5,'⚡ Opportunities'!C:C,"<"&EDATE(AA5,1),'⚡ Opportunities'!F:F,TRUE,'⚡ Opportunities'!G:G,TRUE) -> 49640 | AH5: =EDATE(AH6,-1) -> 45352 | AI5: =COUNTIFS('⚡ Leads'!D:D,">="&AA5,'⚡ Leads'!D:D,"<"&EDATE(AA5,1)) -> 67 | AJ5: =COUNTIFS('⚡ Events'!C:C,">="&AA5,'⚡ Events'!C:C,"<"&EDATE(AA5,1)) -> 93 | AK5: =COUNTIFS('⚡ Opportunities'!C:C,">="&AA5,'⚡ Opportunities'!C:C,"<"&EDATE(AA5,1)) -> 84 | AL5: =COUNTIFS('⚡ Opportunities'!C:C,">="&AA5,'⚡ Opportunities'!C:C,"<"&EDATE(AA5,1),'⚡ Opportunities'!F:F,TRUE,'⚡ Opportunities'!G:G,TRUE) -> 44 | AM5: =SUMIFS('⚡ Opportunities'!H:H,'⚡ Opportunities'!C:C,">="&AA5,'⚡ Opportunities'!C:C,"<"&EDATE(AA5,1),'⚡ Opportunities'!F:F,TRUE,'⚡ Opportunities'!G:G,TRUE) -> 49640 | AO5: =EDATE(AO6,-1) -> 45292 | AP5: =COUNTIFS('⚡ Leads'!D:D,">="&AA5,'⚡ Leads'!D:D,"<"&EDATE(AA5,1)) -> 67 | AQ5: =COUNTIFS('⚡ Events'!C:C,">="&AA5,'⚡ Events'!C:C,"<"&EDATE(AA5,1)) -> 93 | AR5: =COUNTIFS('⚡ Opportunities'!C:C,">="&AA5,'⚡ Opportunities'!C:C,"<"&EDATE(AA5,1)) -> 84 | AS5: =COUNTIFS('⚡ Opportunities'!C:C,">="&AA5,'⚡ Opportunities'!C:C,"<"&EDATE(AA5,1),'⚡ Opportunities'!F:F,TRUE,'⚡ Opportunities'!G:G,TRUE) -> 44 | AT5: =SUMIFS('⚡ Opportunities'!H:H,'⚡ Opportunities'!C:C,">="&AA5,'⚡ Opportunities'!C:C,"<"&EDATE(AA5,1),'⚡ Opportunities'!F:F,TRUE,'⚡ Opportunities'!G:G,TRUE) -> 49640
B6: Forecast Method: | C6: Simple Exponential Smoothing | F6: =IF(C6=AO1,"Smoothing Parameter:","") -> Smoothing Parameter: | G6: 0.8 | H6: =IF(C6=AH1,"No. of Months to Consider:","") | I6: 12 | R6: 46113 | S6: 89.718724 | T6: 119.42523 | U6: 111.34622 | V6: 61.295684 | W6: 100038.59 | X6: 399755.21 | Y6: $100k | AA6: =EDATE(AA7,-1) -> 45383 | AB6: =COUNTIFS('⚡ Leads'!D:D,">="&AA6,'⚡ Leads'!D:D,"<"&EDATE(AA6,1)) -> 71 | AC6: =COUNTIFS('⚡ Events'!C:C,">="&AA6,'⚡ Events'!C:C,"<"&EDATE(AA6,1)) -> 97 | AD6: =COUNTIFS('⚡ Opportunities'!C:C,">="&AA6,'⚡ Opportunities'!C:C,"<"&EDATE(AA6,1)) -> 86 | AE6: =COUNTIFS('⚡ Opportunities'!C:C,">="&AA6,'⚡ Opportunities'!C:C,"<"&EDATE(AA6,1),'⚡ Opportunities'!F:F,TRUE,'⚡ Opportunities'!G:G,TRUE) -> 39 | AF6: =SUMIFS('⚡ Opportunities'!H:H,'⚡ Opportunities'!C:C,">="&AA6,'⚡ Opportunities'!C:C,"<"&EDATE(AA6,1),'⚡ Opportunities'!F:F,TRUE,'⚡ Opportunities'!G:G,TRUE) -> 54800 | AH6: =EDATE(AH7,-1) -> 45383 | AI6: =COUNTIFS('⚡ Leads'!D:D,">="&AA6,'⚡ Leads'!D:D,"<"&EDATE(AA6,1)) -> 71 | AJ6: =COUNTIFS('⚡ Events'!C:C,">="&AA6,'⚡ Events'!C:C,"<"&EDATE(AA6,1)) -> 97 | AK6: =COUNTIFS('⚡ Opportunities'!C:C,">="&AA6,'⚡ Opportunities'!C:C,"<"&EDATE(AA6,1)) -> 86 | AL6: =COUNTIFS('⚡ Opportunities'!C:C,">="&AA6,'⚡ Opportunities'!C:C,"<"&EDATE(AA6,1),'⚡ Opportunities'!F:F,TRUE,'⚡ Opportunities'!G:G,TRUE) -> 39 | AM6: =SUMIFS('⚡ Opportunities'!H:H,'⚡ Opportunities'!C:C,">="&AA6,'⚡ Opportunities'!C:C,"<"&EDATE(AA6,1),'⚡ Opportunities'!F:F,TRUE,'⚡ Opportunities'!G:G,TRUE) -> 54800 | AO6: =EDATE(AO7,-1) -> 45323 | AP6: =COUNTIFS('⚡ Leads'!D:D,">="&AA6,'⚡ Leads'!D:D,"<"&EDATE(AA6,1)) -> 71 | AQ6: =COUNTIFS('⚡ Events'!C:C,">="&AA6,'⚡ Events'!C:C,"<"&EDATE(AA6,1)) -> 97 | AR6: =COUNTIFS('⚡ Opportunities'!C:C,">="&AA6,'⚡ Opportunities'!C:C,"<"&EDATE(AA6,1)) -> 86 | AS6: =COUNTIFS('⚡ Opportunities'!C:C,">="&AA6,'⚡ Opportunities'!C:C,"<"&EDATE(AA6,1),'⚡ Opportunities'!F:F,TRUE,'⚡ Opportunities'!G:G,TRUE) -> 39 | AT6: =SUMIFS('⚡ Opportunities'!H:H,'⚡ Opportunities'!C:C,">="&AA6,'⚡ Opportunities'!C:C,"<"&EDATE(AA6,1),'⚡ Opportunities'!F:F,TRUE,'⚡ Opportunities'!G:G,TRUE) -> 54800
C7: =IF(C6=AA1,"***The method utilizes a minimum of two years' worth of historical data. Use of this method with less than two years of data may result in inaccurate or unreliable forecasts.", IF(C6=AH1,"***This method averages data over the past five months, and assumes consistent patterns over time. Limited or highly fluctuating data may not reflect actual trends accurately,", IF(C6=AO1,"*** This method uses a smoothing parameter that assigns more weight to more recent data. While effective for steady trends, its accuracy may be compromised if the dataset is too short or contains irregular patterns.", "***Select forecasting method."))) -> *** This method uses a smoothing parameter that assigns more weight to more recent data. While effective for steady trends, its accuracy may be compromised if the dataset is too short or contains irregular patterns. | R7: 46143 | S7: 90.003562 | T7: 119.78335 | U7: 111.73633 | V7: 61.400693 | W7: 99437.794 | X7: 499193.01 | Y7: $99k | AA7: =EDATE(AA8,-1) -> 45413 | AB7: =COUNTIFS('⚡ Leads'!D:D,">="&AA7,'⚡ Leads'!D:D,"<"&EDATE(AA7,1)) -> 75 | AC7: =COUNTIFS('⚡ Events'!C:C,">="&AA7,'⚡ Events'!C:C,"<"&EDATE(AA7,1)) -> 100 | AD7: =COUNTIFS('⚡ Opportunities'!C:C,">="&AA7,'⚡ Opportunities'!C:C,"<"&EDATE(AA7,1)) -> 93 | AE7: =COUNTIFS('⚡ Opportunities'!C:C,">="&AA7,'⚡ Opportunities'!C:C,"<"&EDATE(AA7,1),'⚡ Opportunities'!F:F,TRUE,'⚡ Opportunities'!G:G,TRUE) -> 42 | AF7: =SUMIFS('⚡ Opportunities'!H:H,'⚡ Opportunities'!C:C,">="&AA7,'⚡ Opportunities'!C:C,"<"&EDATE(AA7,1),'⚡ Opportunities'!F:F,TRUE,'⚡ Opportunities'!G:G,TRUE) -> 54350 | AH7: =EDATE(AH8,-1) -> 45413 | AI7: =COUNTIFS('⚡ Leads'!D:D,">="&AA7,'⚡ Leads'!D:D,"<"&EDATE(AA7,1)) -> 75 | AJ7: =COUNTIFS('⚡ Events'!C:C,">="&AA7,'⚡ Events'!C:C,"<"&EDATE(AA7,1)) -> 100 | AK7: =COUNTIFS('⚡ Opportunities'!C:C,">="&AA7,'⚡ Opportunities'!C:C,"<"&EDATE(AA7,1)) -> 93 | AL7: =COUNTIFS('⚡ Opportunities'!C:C,">="&AA7,'⚡ Opportunities'!C:C,"<"&EDATE(AA7,1),'⚡ Opportunities'!F:F,TRUE,'⚡ Opportunities'!G:G,TRUE) -> 42 | AM7: =SUMIFS('⚡ Opportunities'!H:H,'⚡ Opportunities'!C:C,">="&AA7,'⚡ Opportunities'!C:C,"<"&EDATE(AA7,1),'⚡ Opportunities'!F:F,TRUE,'⚡ Opportunities'!G:G,TRUE) -> 54350 | AO7: =EDATE(AO8,-1) -> 45352 | AP7: =COUNTIFS('⚡ Leads'!D:D,">="&AA7,'⚡ Leads'!D:D,"<"&EDATE(AA7,1)) -> 75 | AQ7: =COUNTIFS('⚡ Events'!C:C,">="&AA7,'⚡ Events'!C:C,"<"&EDATE(AA7,1)) -> 100 | AR7: =COUNTIFS('⚡ Opportunities'!C:C,">="&AA7,'⚡ Opportunities'!C:C,"<"&EDATE(AA7,1)) -> 93 | AS7: =COUNTIFS('⚡ Opportunities'!C:C,">="&AA7,'⚡ Opportunities'!C:C,"<"&EDATE(AA7,1),'⚡ Opportunities'!F:F,TRUE,'⚡ Opportunities'!G:G,TRUE) -> 42 | AT7: =SUMIFS('⚡ Opportunities'!H:H,'⚡ Opportunities'!C:C,">="&AA7,'⚡ Opportunities'!C:C,"<"&EDATE(AA7,1),'⚡ Opportunities'!F:F,TRUE,'⚡ Opportunities'!G:G,TRUE) -> 54350
R8: 46174 | S8: 90.266768 | T8: 120.09083 | U8: 112.10414 | V8: 61.642356 | W8: 99384.072 | X8: 598577.08 | Y8: $99k | AA8: =EDATE(AA9,-1) -> 45444 | AB8: =COUNTIFS('⚡ Leads'!D:D,">="&AA8,'⚡ Leads'!D:D,"<"&EDATE(AA8,1)) -> 72 | AC8: =COUNTIFS('⚡ Events'!C:C,">="&AA8,'⚡ Events'!C:C,"<"&EDATE(AA8,1)) -> 98 | AD8: =COUNTIFS('⚡ Opportunities'!C:C,">="&AA8,'⚡ Opportunities'!C:C,"<"&EDATE(AA8,1)) -> 90 | AE8: =COUNTIFS('⚡ Opportunities'!C:C,">="&AA8,'⚡ Opportunities'!C:C,"<"&EDATE(AA8,1),'⚡ Opportunities'!F:F,TRUE,'⚡ Opportunities'!G:G,TRUE) -> 60 | AF8: =SUMIFS('⚡ Opportunities'!H:H,'⚡ Opportunities'!C:C,">="&AA8,'⚡ Opportunities'!C:C,"<"&EDATE(AA8,1),'⚡ Opportunities'!F:F,TRUE,'⚡ Opportunities'!G:G,TRUE) -> 122640 | AH8: =EDATE(AH9,-1) -> 45444 | AI8: =COUNTIFS('⚡ Leads'!D:D,">="&AA8,'⚡ Leads'!D:D,"<"&EDATE(AA8,1)) -> 72 | AJ8: =COUNTIFS('⚡ Events'!C:C,">="&AA8,'⚡ Events'!C:C,"<"&EDATE(AA8,1)) -> 98 | AK8: =COUNTIFS('⚡ Opportunities'!C:C,">="&AA8,'⚡ Opportunities'!C:C,"<"&EDATE(AA8,1)) -> 90 | AL8: =COUNTIFS('⚡ Opportunities'!C:C,">="&AA8,'⚡ Opportunities'!C:C,"<"&EDATE(AA8,1),'⚡ Opportunities'!F:F,TRUE,'⚡ Opportunities'!G:G,TRUE) -> 60 | AM8: =SUMIFS('⚡ Opportunities'!H:H,'⚡ Opportunities'!C:C,">="&AA8,'⚡ Opportunities'!C:C,"<"&EDATE(AA8,1),'⚡ Opportunities'!F:F,TRUE,'⚡ Opportunities'!G:G,TRUE) -> 122640 | AO8: =EDATE(AO9,-1) -> 45383 | AP8: =COUNTIFS('⚡ Leads'!D:D,">="&AA8,'⚡ Leads'!D:D,"<"&EDATE(AA8,1)) -> 72 | AQ8: =COUNTIFS('⚡ Events'!C:C,">="&AA8,'⚡ Events'!C:C,"<"&EDATE(AA8,1)) -> 98 | AR8: =COUNTIFS('⚡ Opportunities'!C:C,">="&AA8,'⚡ Opportunities'!C:C,"<"&EDATE(AA8,1)) -> 90 | AS8: =COUNTIFS('⚡ Opportunities'!C:C,">="&AA8,'⚡ Opportunities'!C:C,"<"&EDATE(AA8,1),'⚡ Opportunities'!F:F,TRUE,'⚡ Opportunities'!G:G,TRUE) -> 60 | AT8: =SUMIFS('⚡ Opportunities'!H:H,'⚡ Opportunities'!C:C,">="&AA8,'⚡ Opportunities'!C:C,"<"&EDATE(AA8,1),'⚡ Opportunities'!F:F,TRUE,'⚡ Opportunities'!G:G,TRUE) -> 122640
R9: 46204 | S9: 90.480472 | T9: 120.34964 | U9: 112.41139 | V9: 61.902067 | W9: 99638.671 | X9: 698215.75 | Y9: $100k | AA9: =EDATE(AA10,-1) -> 45474 | AB9: =COUNTIFS('⚡ Leads'!D:D,">="&AA9,'⚡ Leads'!D:D,"<"&EDATE(AA9,1)) -> 77 | AC9: =COUNTIFS('⚡ Events'!C:C,">="&AA9,'⚡ Events'!C:C,"<"&EDATE(AA9,1)) -> 104 | AD9: =COUNTIFS('⚡ Opportunities'!C:C,">="&AA9,'⚡ Opportunities'!C:C,"<"&EDATE(AA9,1)) -> 96 | AE9: =COUNTIFS('⚡ Opportunities'!C:C,">="&AA9,'⚡ Opportunities'!C:C,"<"&EDATE(AA9,1),'⚡ Opportunities'!F:F,TRUE,'⚡ Opportunities'!G:G,TRUE) -> 55 | AF9: =SUMIFS('⚡ Opportunities'!H:H,'⚡ Opportunities'!C:C,">="&AA9,'⚡ Opportunities'!C:C,"<"&EDATE(AA9,1),'⚡ Opportunities'!F:F,TRUE,'⚡ Opportunities'!G:G,TRUE) -> 79860 | AH9: =EDATE(AH10,-1) -> 45474 | AI9: =COUNTIFS('⚡ Leads'!D:D,">="&AA9,'⚡ Leads'!D:D,"<"&EDATE(AA9,1)) -> 77 | AJ9: =COUNTIFS('⚡ Events'!C:C,">="&AA9,'⚡ Events'!C:C,"<"&EDATE(AA9,1)) -> 104 | AK9: =COUNTIFS('⚡ Opportunities'!C:C,">="&AA9,'⚡ Opportunities'!C:C,"<"&EDATE(AA9,1)) -> 96 | AL9: =COUNTIFS('⚡ Opportunities'!C:C,">="&AA9,'⚡ Opportunities'!C:C,"<"&EDATE(AA9,1),'⚡ Opportunities'!F:F,TRUE,'⚡ Opportunities'!G:G,TRUE) -> 55 | AM9: =SUMIFS('⚡ Opportunities'!H:H,'⚡ Opportunities'!C:C,">="&AA9,'⚡ Opportunities'!C:C,"<"&EDATE(AA9,1),'⚡ Opportunities'!F:F,TRUE,'⚡ Opportunities'!G:G,TRUE) -> 79860 | AO9: =EDATE(AO10,-1) -> 45413 | AP9: =COUNTIFS('⚡ Leads'!D:D,">="&AA9,'⚡ Leads'!D:D,"<"&EDATE(AA9,1)) -> 77 | AQ9: =COUNTIFS('⚡ Events'!C:C,">="&AA9,'⚡ Events'!C:C,"<"&EDATE(AA9,1)) -> 104 | AR9: =COUNTIFS('⚡ Opportunities'!C:C,">="&AA9,'⚡ Opportunities'!C:C,"<"&EDATE(AA9,1)) -> 96 | AS9: =COUNTIFS('⚡ Opportunities'!C:C,">="&AA9,'⚡ Opportunities'!C:C,"<"&EDATE(AA9,1),'⚡ Opportunities'!F:F,TRUE,'⚡ Opportunities'!G:G,TRUE) -> 55 | AT9: =SUMIFS('⚡ Opportunities'!H:H,'⚡ Opportunities'!C:C,">="&AA9,'⚡ Opportunities'!C:C,"<"&EDATE(AA9,1),'⚡ Opportunities'!F:F,TRUE,'⚡ Opportunities'!G:G,TRUE) -> 79860
B10: Average Count of New Leads (Previous Three Months) | D10: Average Deal Size (Previous Three Months) | F10: Total Forecasted Leads (in 12 Months) | H10: Total Forecasted Meetings Booked (in 12 Months) | J10: Total Forecasted Closed/Won (in 12 Months) | L10: Total Forecasted Revenue (in 12 Months) | N10: Total Forecasted Revenue (in 24 Months) | R10: 46235 | S10: 90.633558 | T10: 120.54904 | U10: 112.63849 | V10: 62.04986 | W10: 99836.217 | X10: 798051.97 | Y10: $100k | AA10: =EDATE(AA11,-1) -> 45505 | AB10: =COUNTIFS('⚡ Leads'!D:D,">="&AA10,'⚡ Leads'!D:D,"<"&EDATE(AA10,1)) -> 80 | AC10: =COUNTIFS('⚡ Events'!C:C,">="&AA10,'⚡ Events'!C:C,"<"&EDATE(AA10,1)) -> 107 | AD10: =COUNTIFS('⚡ Opportunities'!C:C,">="&AA10,'⚡ Opportunities'!C:C,"<"&EDATE(AA10,1)) -> 99 | AE10: =COUNTIFS('⚡ Opportunities'!C:C,">="&AA10,'⚡ Opportunities'!C:C,"<"&EDATE(AA10,1),'⚡ Opportunities'!F:F,TRUE,'⚡ Opportunities'!G:G,TRUE) -> 60 | AF10: =SUMIFS('⚡ Opportunities'!H:H,'⚡ Opportunities'!C:C,">="&AA10,'⚡ Opportunities'!C:C,"<"&EDATE(AA10,1),'⚡ Opportunities'!F:F,TRUE,'⚡ Opportunities'!G:G,TRUE) -> 128540 | AH10: =EDATE(AH11,-1) -> 45505 | AI10: =COUNTIFS('⚡ Leads'!D:D,">="&AA10,'⚡ Leads'!D:D,"<"&EDATE(AA10,1)) -> 80 | AJ10: =COUNTIFS('⚡ Events'!C:C,">="&AA10,'⚡ Events'!C:C,"<"&EDATE(AA10,1)) -> 107 | AK10: =COUNTIFS('⚡ Opportunities'!C:C,">="&AA10,'⚡ Opportunities'!C:C,"<"&EDATE(AA10,1)) -> 99 | AL10: =COUNTIFS('⚡ Opportunities'!C:C,">="&AA10,'⚡ Opportunities'!C:C,"<"&EDATE(AA10,1),'⚡ Opportunities'!F:F,TRUE,'⚡ Opportunities'!G:G,TRUE) -> 60 | AM10: =SUMIFS('⚡ Opportunities'!H:H,'⚡ Opportunities'!C:C,">="&AA10,'⚡ Opportunities'!C:C,"<"&EDATE(AA10,1),'⚡ Opportunities'!F:F,TRUE,'⚡ Opportunities'!G:G,TRUE) -> 128540 | AO10: =EDATE(AO11,-1) -> 45444 | AP10: =COUNTIFS('⚡ Leads'!D:D,">="&AA10,'⚡ Leads'!D:D,"<"&EDATE(AA10,1)) -> 80 | AQ10: =COUNTIFS('⚡ Events'!C:C,">="&AA10,'⚡ Events'!C:C,"<"&EDATE(AA10,1)) -> 107 | AR10: =COUNTIFS('⚡ Opportunities'!C:C,">="&AA10,'⚡ Opportunities'!C:C,"<"&EDATE(AA10,1)) -> 99 | AS10: =COUNTIFS('⚡ Opportunities'!C:C,">="&AA10,'⚡ Opportunities'!C:C,"<"&EDATE(AA10,1),'⚡ Opportunities'!F:F,TRUE,'⚡ Opportunities'!G:G,TRUE) -> 60 | AT10: =SUMIFS('⚡ Opportunities'!H:H,'⚡ Opportunities'!C:C,">="&AA10,'⚡ Opportunities'!C:C,"<"&EDATE(AA10,1),'⚡ Opportunities'!F:F,TRUE,'⚡ Opportunities'!G:G,TRUE) -> 128540
B11: 109 | D11: 1691.8508 | F11: =SUM(D16:O16) -> 1081.3696 | H11: =SUM(D17:O17) -> 1438.7012 | J11: =SUM(D19:O19) -> 741.06738 | L11: =O22 -> 1197230.8 | N11: =X26 -> 2392056.2 | R11: 46266 | S11: 90.728186 | T11: 120.6562 | U11: 112.76886 | V11: 62.21574 | W11: 100041.74 | X11: 898093.71 | Y11: $100k | AA11: =EDATE(AA12,-1) -> 45536 | AB11: =COUNTIFS('⚡ Leads'!D:D,">="&AA11,'⚡ Leads'!D:D,"<"&EDATE(AA11,1)) -> 78 | AC11: =COUNTIFS('⚡ Events'!C:C,">="&AA11,'⚡ Events'!C:C,"<"&EDATE(AA11,1)) -> 106 | AD11: =COUNTIFS('⚡ Opportunities'!C:C,">="&AA11,'⚡ Opportunities'!C:C,"<"&EDATE(AA11,1)) -> 95 | AE11: =COUNTIFS('⚡ Opportunities'!C:C,">="&AA11,'⚡ Opportunities'!C:C,"<"&EDATE(AA11,1),'⚡ Opportunities'!F:F,TRUE,'⚡ Opportunities'!G:G,TRUE) -> 59 | AF11: =SUMIFS('⚡ Opportunities'!H:H,'⚡ Opportunities'!C:C,">="&AA11,'⚡ Opportunities'!C:C,"<"&EDATE(AA11,1),'⚡ Opportunities'!F:F,TRUE,'⚡ Opportunities'!G:G,TRUE) -> 108840 | AH11: =EDATE(AH12,-1) -> 45536 | AI11: =COUNTIFS('⚡ Leads'!D:D,">="&AA11,'⚡ Leads'!D:D,"<"&EDATE(AA11,1)) -> 78 | AJ11: =COUNTIFS('⚡ Events'!C:C,">="&AA11,'⚡ Events'!C:C,"<"&EDATE(AA11,1)) -> 106 | AK11: =COUNTIFS('⚡ Opportunities'!C:C,">="&AA11,'⚡ Opportunities'!C:C,"<"&EDATE(AA11,1)) -> 95 | AL11: =COUNTIFS('⚡ Opportunities'!C:C,">="&AA11,'⚡ Opportunities'!C:C,"<"&EDATE(AA11,1),'⚡ Opportunities'!F:F,TRUE,'⚡ Opportunities'!G:G,TRUE) -> 59 | AM11: =SUMIFS('⚡ Opportunities'!H:H,'⚡ Opportunities'!C:C,">="&AA11,'⚡ Opportunities'!C:C,"<"&EDATE(AA11,1),'⚡ Opportunities'!F:F,TRUE,'⚡ Opportunities'!G:G,TRUE) -> 108840 | AO11: =EDATE(AO12,-1) -> 45474 | AP11: =COUNTIFS('⚡ Leads'!D:D,">="&AA11,'⚡ Leads'!D:D,"<"&EDATE(AA11,1)) -> 78 | AQ11: =COUNTIFS('⚡ Events'!C:C,">="&AA11,'⚡ Events'!C:C,"<"&EDATE(AA11,1)) -> 106 | AR11: =COUNTIFS('⚡ Opportunities'!C:C,">="&AA11,'⚡ Opportunities'!C:C,"<"&EDATE(AA11,1)) -> 95 | AS11: =COUNTIFS('⚡ Opportunities'!C:C,">="&AA11,'⚡ Opportunities'!C:C,"<"&EDATE(AA11,1),'⚡ Opportunities'!F:F,TRUE,'⚡ Opportunities'!G:G,TRUE) -> 59 | AT11: =SUMIFS('⚡ Opportunities'!H:H,'⚡ Opportunities'!C:C,">="&AA11,'⚡ Opportunities'!C:C,"<"&EDATE(AA11,1),'⚡ Opportunities'!F:F,TRUE,'⚡ Opportunities'!G:G,TRUE) -> 108840
R12: 46296 | S12: 90.753632 | T12: 120.65552 | U12: 112.77632 | V12: 62.339217 | W12: 99855.707 | X12: 997949.41 | Y12: $100k | AA12: =EDATE(AA13,-1) -> 45566 | AB12: =COUNTIFS('⚡ Leads'!D:D,">="&AA12,'⚡ Leads'!D:D,"<"&EDATE(AA12,1)) -> 82 | AC12: =COUNTIFS('⚡ Events'!C:C,">="&AA12,'⚡ Events'!C:C,"<"&EDATE(AA12,1)) -> 111 | AD12: =COUNTIFS('⚡ Opportunities'!C:C,">="&AA12,'⚡ Opportunities'!C:C,"<"&EDATE(AA12,1)) -> 101 | AE12: =COUNTIFS('⚡ Opportunities'!C:C,">="&AA12,'⚡ Opportunities'!C:C,"<"&EDATE(AA12,1),'⚡ Opportunities'!F:F,TRUE,'⚡ Opportunities'!G:G,TRUE) -> 51 | AF12: =SUMIFS('⚡ Opportunities'!H:H,'⚡ Opportunities'!C:C,">="&AA12,'⚡ Opportunities'!C:C,"<"&EDATE(AA12,1),'⚡ Opportunities'!F:F,TRUE,'⚡ Opportunities'!G:G,TRUE) -> 95780 | AH12: =EDATE(AH13,-1) -> 45566 | AI12: =COUNTIFS('⚡ Leads'!D:D,">="&AA12,'⚡ Leads'!D:D,"<"&EDATE(AA12,1)) -> 82 | AJ12: =COUNTIFS('⚡ Events'!C:C,">="&AA12,'⚡ Events'!C:C,"<"&EDATE(AA12,1)) -> 111 | AK12: =COUNTIFS('⚡ Opportunities'!C:C,">="&AA12,'⚡ Opportunities'!C:C,"<"&EDATE(AA12,1)) -> 101 | AL12: =COUNTIFS('⚡ Opportunities'!C:C,">="&AA12,'⚡ Opportunities'!C:C,"<"&EDATE(AA12,1),'⚡ Opportunities'!F:F,TRUE,'⚡ Opportunities'!G:G,TRUE) -> 51 | AM12: =SUMIFS('⚡ Opportunities'!H:H,'⚡ Opportunities'!C:C,">="&AA12,'⚡ Opportunities'!C:C,"<"&EDATE(AA12,1),'⚡ Opportunities'!F:F,TRUE,'⚡ Opportunities'!G:G,TRUE) -> 95780 | AO12: =EDATE(AO13,-1) -> 45505 | AP12: =COUNTIFS('⚡ Leads'!D:D,">="&AA12,'⚡ Leads'!D:D,"<"&EDATE(AA12,1)) -> 82 | AQ12: =COUNTIFS('⚡ Events'!C:C,">="&AA12,'⚡ Events'!C:C,"<"&EDATE(AA12,1)) -> 111 | AR12: =COUNTIFS('⚡ Opportunities'!C:C,">="&AA12,'⚡ Opportunities'!C:C,"<"&EDATE(AA12,1)) -> 101 | AS12: =COUNTIFS('⚡ Opportunities'!C:C,">="&AA12,'⚡ Opportunities'!C:C,"<"&EDATE(AA12,1),'⚡ Opportunities'!F:F,TRUE,'⚡ Opportunities'!G:G,TRUE) -> 51 | AT12: =SUMIFS('⚡ Opportunities'!H:H,'⚡ Opportunities'!C:C,">="&AA12,'⚡ Opportunities'!C:C,"<"&EDATE(AA12,1),'⚡ Opportunities'!F:F,TRUE,'⚡ Opportunities'!G:G,TRUE) -> 95780
R13: 46327 | S13: 90.676973 | T13: 120.54505 | U13: 112.66201 | V13: 62.336107 | W13: 99698.242 | X13: 1097647.7 | Y13: $100k | AA13: =EDATE(AA14,-1) -> 45597 | AB13: =COUNTIFS('⚡ Leads'!D:D,">="&AA13,'⚡ Leads'!D:D,"<"&EDATE(AA13,1)) -> 86 | AC13: =COUNTIFS('⚡ Events'!C:C,">="&AA13,'⚡ Events'!C:C,"<"&EDATE(AA13,1)) -> 114 | AD13: =COUNTIFS('⚡ Opportunities'!C:C,">="&AA13,'⚡ Opportunities'!C:C,"<"&EDATE(AA13,1)) -> 105 | AE13: =COUNTIFS('⚡ Opportunities'!C:C,">="&AA13,'⚡ Opportunities'!C:C,"<"&EDATE(AA13,1),'⚡ Opportunities'!F:F,TRUE,'⚡ Opportunities'!G:G,TRUE) -> 60 | AF13: =SUMIFS('⚡ Opportunities'!H:H,'⚡ Opportunities'!C:C,">="&AA13,'⚡ Opportunities'!C:C,"<"&EDATE(AA13,1),'⚡ Opportunities'!F:F,TRUE,'⚡ Opportunities'!G:G,TRUE) -> 155620 | AH13: =EDATE(AH14,-1) -> 45597 | AI13: =COUNTIFS('⚡ Leads'!D:D,">="&AA13,'⚡ Leads'!D:D,"<"&EDATE(AA13,1)) -> 86 | AJ13: =COUNTIFS('⚡ Events'!C:C,">="&AA13,'⚡ Events'!C:C,"<"&EDATE(AA13,1)) -> 114 | AK13: =COUNTIFS('⚡ Opportunities'!C:C,">="&AA13,'⚡ Opportunities'!C:C,"<"&EDATE(AA13,1)) -> 105 | AL13: =COUNTIFS('⚡ Opportunities'!C:C,">="&AA13,'⚡ Opportunities'!C:C,"<"&EDATE(AA13,1),'⚡ Opportunities'!F:F,TRUE,'⚡ Opportunities'!G:G,TRUE) -> 60 | AM13: =SUMIFS('⚡ Opportunities'!H:H,'⚡ Opportunities'!C:C,">="&AA13,'⚡ Opportunities'!C:C,"<"&EDATE(AA13,1),'⚡ Opportunities'!F:F,TRUE,'⚡ Opportunities'!G:G,TRUE) -> 155620 | AO13: =EDATE(AO14,-1) -> 45536 | AP13: =COUNTIFS('⚡ Leads'!D:D,">="&AA13,'⚡ Leads'!D:D,"<"&EDATE(AA13,1)) -> 86 | AQ13: =COUNTIFS('⚡ Events'!C:C,">="&AA13,'⚡ Events'!C:C,"<"&EDATE(AA13,1)) -> 114 | AR13: =COUNTIFS('⚡ Opportunities'!C:C,">="&AA13,'⚡ Opportunities'!C:C,"<"&EDATE(AA13,1)) -> 105 | AS13: =COUNTIFS('⚡ Opportunities'!C:C,">="&AA13,'⚡ Opportunities'!C:C,"<"&EDATE(AA13,1),'⚡ Opportunities'!F:F,TRUE,'⚡ Opportunities'!G:G,TRUE) -> 60 | AT13: =SUMIFS('⚡ Opportunities'!H:H,'⚡ Opportunities'!C:C,">="&AA13,'⚡ Opportunities'!C:C,"<"&EDATE(AA13,1),'⚡ Opportunities'!F:F,TRUE,'⚡ Opportunities'!G:G,TRUE) -> 155620
D14: =EOMONTH(TODAY(),-1)+1 -> 46023 | E14: 45778 | F14: 45809 | G14: 45839 | H14: 45870 | I14: 45901 | J14: 45931 | K14: 45962 | L14: 45992 | M14: 46023 | N14: 46054 | O14: 46082 | R14: 46357 | S14: 90.561464 | T14: 120.39665 | U14: 112.50361 | V14: 62.272106 | W14: 99583.123 | X14: 1197230.8 | Y14: $100k | AA14: =EDATE(AA15,-1) -> 45627 | AB14: =COUNTIFS('⚡ Leads'!D:D,">="&AA14,'⚡ Leads'!D:D,"<"&EDATE(AA14,1)) -> 87 | AC14: =COUNTIFS('⚡ Events'!C:C,">="&AA14,'⚡ Events'!C:C,"<"&EDATE(AA14,1)) -> 118 | AD14: =COUNTIFS('⚡ Opportunities'!C:C,">="&AA14,'⚡ Opportunities'!C:C,"<"&EDATE(AA14,1)) -> 107 | AE14: =COUNTIFS('⚡ Opportunities'!C:C,">="&AA14,'⚡ Opportunities'!C:C,"<"&EDATE(AA14,1),'⚡ Opportunities'!F:F,TRUE,'⚡ Opportunities'!G:G,TRUE) -> 48 | AF14: =SUMIFS('⚡ Opportunities'!H:H,'⚡ Opportunities'!C:C,">="&AA14,'⚡ Opportunities'!C:C,"<"&EDATE(AA14,1),'⚡ Opportunities'!F:F,TRUE,'⚡ Opportunities'!G:G,TRUE) -> 63150 | AH14: =EDATE(AH15,-1) -> 45627 | AI14: =COUNTIFS('⚡ Leads'!D:D,">="&AA14,'⚡ Leads'!D:D,"<"&EDATE(AA14,1)) -> 87 | AJ14: =COUNTIFS('⚡ Events'!C:C,">="&AA14,'⚡ Events'!C:C,"<"&EDATE(AA14,1)) -> 118 | AK14: =COUNTIFS('⚡ Opportunities'!C:C,">="&AA14,'⚡ Opportunities'!C:C,"<"&EDATE(AA14,1)) -> 107 | AL14: =COUNTIFS('⚡ Opportunities'!C:C,">="&AA14,'⚡ Opportunities'!C:C,"<"&EDATE(AA14,1),'⚡ Opportunities'!F:F,TRUE,'⚡ Opportunities'!G:G,TRUE) -> 48 | AM14: =SUMIFS('⚡ Opportunities'!H:H,'⚡ Opportunities'!C:C,">="&AA14,'⚡ Opportunities'!C:C,"<"&EDATE(AA14,1),'⚡ Opportunities'!F:F,TRUE,'⚡ Opportunities'!G:G,TRUE) -> 63150 | AO14: =EDATE(AO15,-1) -> 45566 | AP14: =COUNTIFS('⚡ Leads'!D:D,">="&AA14,'⚡ Leads'!D:D,"<"&EDATE(AA14,1)) -> 87 | AQ14: =COUNTIFS('⚡ Events'!C:C,">="&AA14,'⚡ Events'!C:C,"<"&EDATE(AA14,1)) -> 118 | AR14: =COUNTIFS('⚡ Opportunities'!C:C,">="&AA14,'⚡ Opportunities'!C:C,"<"&EDATE(AA14,1)) -> 107 | AS14: =COUNTIFS('⚡ Opportunities'!C:C,">="&AA14,'⚡ Opportunities'!C:C,"<"&EDATE(AA14,1),'⚡ Opportunities'!F:F,TRUE,'⚡ Opportunities'!G:G,TRUE) -> 48 | AT14: =SUMIFS('⚡ Opportunities'!H:H,'⚡ Opportunities'!C:C,">="&AA14,'⚡ Opportunities'!C:C,"<"&EDATE(AA14,1),'⚡ Opportunities'!F:F,TRUE,'⚡ Opportunities'!G:G,TRUE) -> 63150
R15: 46388 | S15: 90.443624 | T15: 120.25122 | U15: 112.34567 | V15: 62.187434 | W15: 99513.78 | X15: 1296744.6 | Y15: $100k | AA15: =EDATE(AA16,-1) -> 45658 | AB15: =COUNTIFS('⚡ Leads'!D:D,">="&AA15,'⚡ Leads'!D:D,"<"&EDATE(AA15,1)) -> 90 | AC15: =COUNTIFS('⚡ Events'!C:C,">="&AA15,'⚡ Events'!C:C,"<"&EDATE(AA15,1)) -> 119 | AD15: =COUNTIFS('⚡ Opportunities'!C:C,">="&AA15,'⚡ Opportunities'!C:C,"<"&EDATE(AA15,1)) -> 111 | AE15: =COUNTIFS('⚡ Opportunities'!C:C,">="&AA15,'⚡ Opportunities'!C:C,"<"&EDATE(AA15,1),'⚡ Opportunities'!F:F,TRUE,'⚡ Opportunities'!G:G,TRUE) -> 56 | AF15: =SUMIFS('⚡ Opportunities'!H:H,'⚡ Opportunities'!C:C,">="&AA15,'⚡ Opportunities'!C:C,"<"&EDATE(AA15,1),'⚡ Opportunities'!F:F,TRUE,'⚡ Opportunities'!G:G,TRUE) -> 74090 | AH15: =EDATE(AH16,-1) -> 45658 | AI15: =COUNTIFS('⚡ Leads'!D:D,">="&AA15,'⚡ Leads'!D:D,"<"&EDATE(AA15,1)) -> 90 | AJ15: =COUNTIFS('⚡ Events'!C:C,">="&AA15,'⚡ Events'!C:C,"<"&EDATE(AA15,1)) -> 119 | AK15: =COUNTIFS('⚡ Opportunities'!C:C,">="&AA15,'⚡ Opportunities'!C:C,"<"&EDATE(AA15,1)) -> 111 | AL15: =COUNTIFS('⚡ Opportunities'!C:C,">="&AA15,'⚡ Opportunities'!C:C,"<"&EDATE(AA15,1),'⚡ Opportunities'!F:F,TRUE,'⚡ Opportunities'!G:G,TRUE) -> 56 | AM15: =SUMIFS('⚡ Opportunities'!H:H,'⚡ Opportunities'!C:C,">="&AA15,'⚡ Opportunities'!C:C,"<"&EDATE(AA15,1),'⚡ Opportunities'!F:F,TRUE,'⚡ Opportunities'!G:G,TRUE) -> 74090 | AO15: =EDATE(AO16,-1) -> 45597 | AP15: =COUNTIFS('⚡ Leads'!D:D,">="&AA15,'⚡ Leads'!D:D,"<"&EDATE(AA15,1)) -> 90 | AQ15: =COUNTIFS('⚡ Events'!C:C,">="&AA15,'⚡ Events'!C:C,"<"&EDATE(AA15,1)) -> 119 | AR15: =COUNTIFS('⚡ Opportunities'!C:C,">="&AA15,'⚡ Opportunities'!C:C,"<"&EDATE(AA15,1)) -> 111 | AS15: =COUNTIFS('⚡ Opportunities'!C:C,">="&AA15,'⚡ Opportunities'!C:C,"<"&EDATE(AA15,1),'⚡ Opportunities'!F:F,TRUE,'⚡ Opportunities'!G:G,TRUE) -> 56 | AT15: =SUMIFS('⚡ Opportunities'!H:H,'⚡ Opportunities'!C:C,">="&AA15,'⚡ Opportunities'!C:C,"<"&EDATE(AA15,1),'⚡ Opportunities'!F:F,TRUE,'⚡ Opportunities'!G:G,TRUE) -> 74090
B16: Acquired Leads | D16: {=TRANSPOSE(S3:S14)} -> 88.979183 | E16: 89.149743 | F16: 89.417364 | G16: 89.718724 | H16: 90.003562 | I16: 90.266768 | J16: 90.480472 | K16: 90.633558 | L16: 90.728186 | M16: 90.753632 | N16: 90.676973 | O16: 90.561464 | R16: 46419 | S16: 90.342503 | T16: 120.12945 | U16: 112.21146 | V16: 62.104786 | W16: 99487.152 | X16: 1396231.7 | Y16: $99k | AA16: =EDATE(AA17,-1) -> 45689 | AB16: =COUNTIFS('⚡ Leads'!D:D,">="&AA16,'⚡ Leads'!D:D,"<"&EDATE(AA16,1)) -> 92 | AC16: =COUNTIFS('⚡ Events'!C:C,">="&AA16,'⚡ Events'!C:C,"<"&EDATE(AA16,1)) -> 121 | AD16: =COUNTIFS('⚡ Opportunities'!C:C,">="&AA16,'⚡ Opportunities'!C:C,"<"&EDATE(AA16,1)) -> 114 | AE16: =COUNTIFS('⚡ Opportunities'!C:C,">="&AA16,'⚡ Opportunities'!C:C,"<"&EDATE(AA16,1),'⚡ Opportunities'!F:F,TRUE,'⚡ Opportunities'!G:G,TRUE) -> 67 | AF16: =SUMIFS('⚡ Opportunities'!H:H,'⚡ Opportunities'!C:C,">="&AA16,'⚡ Opportunities'!C:C,"<"&EDATE(AA16,1),'⚡ Opportunities'!F:F,TRUE,'⚡ Opportunities'!G:G,TRUE) -> 100160 | AH16: =EDATE(AH17,-1) -> 45689 | AI16: =COUNTIFS('⚡ Leads'!D:D,">="&AA16,'⚡ Leads'!D:D,"<"&EDATE(AA16,1)) -> 92 | AJ16: =COUNTIFS('⚡ Events'!C:C,">="&AA16,'⚡ Events'!C:C,"<"&EDATE(AA16,1)) -> 121 | AK16: =COUNTIFS('⚡ Opportunities'!C:C,">="&AA16,'⚡ Opportunities'!C:C,"<"&EDATE(AA16,1)) -> 114 | AL16: =COUNTIFS('⚡ Opportunities'!C:C,">="&AA16,'⚡ Opportunities'!C:C,"<"&EDATE(AA16,1),'⚡ Opportunities'!F:F,TRUE,'⚡ Opportunities'!G:G,TRUE) -> 67 | AM16: =SUMIFS('⚡ Opportunities'!H:H,'⚡ Opportunities'!C:C,">="&AA16,'⚡ Opportunities'!C:C,"<"&EDATE(AA16,1),'⚡ Opportunities'!F:F,TRUE,'⚡ Opportunities'!G:G,TRUE) -> 100160 | AO16: =EDATE(AO17,-1) -> 45627 | AP16: =COUNTIFS('⚡ Leads'!D:D,">="&AA16,'⚡ Leads'!D:D,"<"&EDATE(AA16,1)) -> 92 | AQ16: =COUNTIFS('⚡ Events'!C:C,">="&AA16,'⚡ Events'!C:C,"<"&EDATE(AA16,1)) -> 121 | AR16: =COUNTIFS('⚡ Opportunities'!C:C,">="&AA16,'⚡ Opportunities'!C:C,"<"&EDATE(AA16,1)) -> 114 | AS16: =COUNTIFS('⚡ Opportunities'!C:C,">="&AA16,'⚡ Opportunities'!C:C,"<"&EDATE(AA16,1),'⚡ Opportunities'!F:F,TRUE,'⚡ Opportunities'!G:G,TRUE) -> 67 | AT16: =SUMIFS('⚡ Opportunities'!H:H,'⚡ Opportunities'!C:C,">="&AA16,'⚡ Opportunities'!C:C,"<"&EDATE(AA16,1),'⚡ Opportunities'!F:F,TRUE,'⚡ Opportunities'!G:G,TRUE) -> 100160
B17: Meetings Booked | D17: {=TRANSPOSE(T3:V14)} -> 118.47633 | E17: 118.71602 | F17: 119.05736 | G17: 119.42523 | H17: 119.78335 | I17: 120.09083 | J17: 120.34964 | K17: 120.54904 | L17: 120.6562 | M17: 120.65552 | N17: 120.54505 | O17: 120.39665 | R17: 46447 | S17: 90.266219 | T17: 120.0397 | U17: 112.1108 | V17: 62.03574 | W17: 99493.347 | X17: 1495725.1 | Y17: $99k | AA17: =EDATE(AA18,-1) -> 45717 | AB17: =COUNTIFS('⚡ Leads'!D:D,">="&AA17,'⚡ Leads'!D:D,"<"&EDATE(AA17,1)) -> 93 | AC17: =COUNTIFS('⚡ Events'!C:C,">="&AA17,'⚡ Events'!C:C,"<"&EDATE(AA17,1)) -> 125 | AD17: =COUNTIFS('⚡ Opportunities'!C:C,">="&AA17,'⚡ Opportunities'!C:C,"<"&EDATE(AA17,1)) -> 117 | AE17: =COUNTIFS('⚡ Opportunities'!C:C,">="&AA17,'⚡ Opportunities'!C:C,"<"&EDATE(AA17,1),'⚡ Opportunities'!F:F,TRUE,'⚡ Opportunities'!G:G,TRUE) -> 58 | AF17: =SUMIFS('⚡ Opportunities'!H:H,'⚡ Opportunities'!C:C,">="&AA17,'⚡ Opportunities'!C:C,"<"&EDATE(AA17,1),'⚡ Opportunities'!F:F,TRUE,'⚡ Opportunities'!G:G,TRUE) -> 95800 | AH17: =EDATE(AH18,-1) -> 45717 | AI17: =COUNTIFS('⚡ Leads'!D:D,">="&AA17,'⚡ Leads'!D:D,"<"&EDATE(AA17,1)) -> 93 | AJ17: =COUNTIFS('⚡ Events'!C:C,">="&AA17,'⚡ Events'!C:C,"<"&EDATE(AA17,1)) -> 125 | AK17: =COUNTIFS('⚡ Opportunities'!C:C,">="&AA17,'⚡ Opportunities'!C:C,"<"&EDATE(AA17,1)) -> 117 | AL17: =COUNTIFS('⚡ Opportunities'!C:C,">="&AA17,'⚡ Opportunities'!C:C,"<"&EDATE(AA17,1),'⚡ Opportunities'!F:F,TRUE,'⚡ Opportunities'!G:G,TRUE) -> 58 | AM17: =SUMIFS('⚡ Opportunities'!H:H,'⚡ Opportunities'!C:C,">="&AA17,'⚡ Opportunities'!C:C,"<"&EDATE(AA17,1),'⚡ Opportunities'!F:F,TRUE,'⚡ Opportunities'!G:G,TRUE) -> 95800 | AO17: =EDATE(AO18,-1) -> 45658 | AP17: =COUNTIFS('⚡ Leads'!D:D,">="&AA17,'⚡ Leads'!D:D,"<"&EDATE(AA17,1)) -> 93 | AQ17: =COUNTIFS('⚡ Events'!C:C,">="&AA17,'⚡ Events'!C:C,"<"&EDATE(AA17,1)) -> 125 | AR17: =COUNTIFS('⚡ Opportunities'!C:C,">="&AA17,'⚡ Opportunities'!C:C,"<"&EDATE(AA17,1)) -> 117 | AS17: =COUNTIFS('⚡ Opportunities'!C:C,">="&AA17,'⚡ Opportunities'!C:C,"<"&EDATE(AA17,1),'⚡ Opportunities'!F:F,TRUE,'⚡ Opportunities'!G:G,TRUE) -> 58 | AT17: =SUMIFS('⚡ Opportunities'!H:H,'⚡ Opportunities'!C:C,">="&AA17,'⚡ Opportunities'!C:C,"<"&EDATE(AA17,1),'⚡ Opportunities'!F:F,TRUE,'⚡ Opportunities'!G:G,TRUE) -> 95800
B18: New Opportunities | D18: 110.40166 | E18: 110.60535 | F18: 110.9519 | G18: 111.34622 | H18: 111.73633 | I18: 112.10414 | J18: 112.41139 | K18: 112.63849 | L18: 112.76886 | M18: 112.77632 | N18: 112.66201 | O18: 112.50361 | R18: 46478 | S18: 90.216405 | T18: 119.98306 | U18: 112.04517 | V18: 61.983895 | W18: 99519.182 | X18: 1595244.2 | Y18: $100k | AA18: =EDATE(AA19,-1) -> 45748 | AB18: =COUNTIFS('⚡ Leads'!D:D,">="&AA18,'⚡ Leads'!D:D,"<"&EDATE(AA18,1)) -> 95 | AC18: =COUNTIFS('⚡ Events'!C:C,">="&AA18,'⚡ Events'!C:C,"<"&EDATE(AA18,1)) -> 128 | AD18: =COUNTIFS('⚡ Opportunities'!C:C,">="&AA18,'⚡ Opportunities'!C:C,"<"&EDATE(AA18,1)) -> 121 | AE18: =COUNTIFS('⚡ Opportunities'!C:C,">="&AA18,'⚡ Opportunities'!C:C,"<"&EDATE(AA18,1),'⚡ Opportunities'!F:F,TRUE,'⚡ Opportunities'!G:G,TRUE) -> 63 | AF18: =SUMIFS('⚡ Opportunities'!H:H,'⚡ Opportunities'!C:C,">="&AA18,'⚡ Opportunities'!C:C,"<"&EDATE(AA18,1),'⚡ Opportunities'!F:F,TRUE,'⚡ Opportunities'!G:G,TRUE) -> 129830 | AH18: =EDATE(AH19,-1) -> 45748 | AI18: =COUNTIFS('⚡ Leads'!D:D,">="&AA18,'⚡ Leads'!D:D,"<"&EDATE(AA18,1)) -> 95 | AJ18: =COUNTIFS('⚡ Events'!C:C,">="&AA18,'⚡ Events'!C:C,"<"&EDATE(AA18,1)) -> 128 | AK18: =COUNTIFS('⚡ Opportunities'!C:C,">="&AA18,'⚡ Opportunities'!C:C,"<"&EDATE(AA18,1)) -> 121 | AL18: =COUNTIFS('⚡ Opportunities'!C:C,">="&AA18,'⚡ Opportunities'!C:C,"<"&EDATE(AA18,1),'⚡ Opportunities'!F:F,TRUE,'⚡ Opportunities'!G:G,TRUE) -> 63 | AM18: =SUMIFS('⚡ Opportunities'!H:H,'⚡ Opportunities'!C:C,">="&AA18,'⚡ Opportunities'!C:C,"<"&EDATE(AA18,1),'⚡ Opportunities'!F:F,TRUE,'⚡ Opportunities'!G:G,TRUE) -> 129830 | AO18: =EDATE(AO19,-1) -> 45689 | AP18: =COUNTIFS('⚡ Leads'!D:D,">="&AA18,'⚡ Leads'!D:D,"<"&EDATE(AA18,1)) -> 95 | AQ18: =COUNTIFS('⚡ Events'!C:C,">="&AA18,'⚡ Events'!C:C,"<"&EDATE(AA18,1)) -> 128 | AR18: =COUNTIFS('⚡ Opportunities'!C:C,">="&AA18,'⚡ Opportunities'!C:C,"<"&EDATE(AA18,1)) -> 121 | AS18: =COUNTIFS('⚡ Opportunities'!C:C,">="&AA18,'⚡ Opportunities'!C:C,"<"&EDATE(AA18,1),'⚡ Opportunities'!F:F,TRUE,'⚡ Opportunities'!G:G,TRUE) -> 63 | AT18: =SUMIFS('⚡ Opportunities'!H:H,'⚡ Opportunities'!C:C,">="&AA18,'⚡ Opportunities'!C:C,"<"&EDATE(AA18,1),'⚡ Opportunities'!F:F,TRUE,'⚡ Opportunities'!G:G,TRUE) -> 129830
B19: Closed/Won | D19: 61.237095 | E19: 61.192974 | F19: 61.183476 | G19: 61.295684 | H19: 61.400693 | I19: 61.642356 | J19: 61.902067 | K19: 62.04986 | L19: 62.21574 | M19: 62.339217 | N19: 62.336107 | O19: 62.272106 | R19: 46508 | S19: 90.1912 | T19: 119.95645 | U19: 112.01183 | V19: 61.948171 | W19: 99549.678 | X19: 1694793.9 | Y19: $100k | AA19: =EDATE(AA20,-1) -> 45778 | AB19: =COUNTIFS('⚡ Leads'!D:D,">="&AA19,'⚡ Leads'!D:D,"<"&EDATE(AA19,1)) -> 99 | AC19: =COUNTIFS('⚡ Events'!C:C,">="&AA19,'⚡ Events'!C:C,"<"&EDATE(AA19,1)) -> 130 | AD19: =COUNTIFS('⚡ Opportunities'!C:C,">="&AA19,'⚡ Opportunities'!C:C,"<"&EDATE(AA19,1)) -> 123 | AE19: =COUNTIFS('⚡ Opportunities'!C:C,">="&AA19,'⚡ Opportunities'!C:C,"<"&EDATE(AA19,1),'⚡ Opportunities'!F:F,TRUE,'⚡ Opportunities'!G:G,TRUE) -> 71 | AF19: =SUMIFS('⚡ Opportunities'!H:H,'⚡ Opportunities'!C:C,">="&AA19,'⚡ Opportunities'!C:C,"<"&EDATE(AA19,1),'⚡ Opportunities'!F:F,TRUE,'⚡ Opportunities'!G:G,TRUE) -> 100590 | AH19: =EDATE(AH20,-1) -> 45778 | AI19: =COUNTIFS('⚡ Leads'!D:D,">="&AA19,'⚡ Leads'!D:D,"<"&EDATE(AA19,1)) -> 99 | AJ19: =COUNTIFS('⚡ Events'!C:C,">="&AA19,'⚡ Events'!C:C,"<"&EDATE(AA19,1)) -> 130 | AK19: =COUNTIFS('⚡ Opportunities'!C:C,">="&AA19,'⚡ Opportunities'!C:C,"<"&EDATE(AA19,1)) -> 123 | AL19: =COUNTIFS('⚡ Opportunities'!C:C,">="&AA19,'⚡ Opportunities'!C:C,"<"&EDATE(AA19,1),'⚡ Opportunities'!F:F,TRUE,'⚡ Opportunities'!G:G,TRUE) -> 71 | AM19: =SUMIFS('⚡ Opportunities'!H:H,'⚡ Opportunities'!C:C,">="&AA19,'⚡ Opportunities'!C:C,"<"&EDATE(AA19,1),'⚡ Opportunities'!F:F,TRUE,'⚡ Opportunities'!G:G,TRUE) -> 100590 | AO19: =EDATE(AO20,-1) -> 45717 | AP19: =COUNTIFS('⚡ Leads'!D:D,">="&AA19,'⚡ Leads'!D:D,"<"&EDATE(AA19,1)) -> 99 | AQ19: =COUNTIFS('⚡ Events'!C:C,">="&AA19,'⚡ Events'!C:C,"<"&EDATE(AA19,1)) -> 130 | AR19: =COUNTIFS('⚡ Opportunities'!C:C,">="&AA19,'⚡ Opportunities'!C:C,"<"&EDATE(AA19,1)) -> 123 | AS19: =COUNTIFS('⚡ Opportunities'!C:C,">="&AA19,'⚡ Opportunities'!C:C,"<"&EDATE(AA19,1),'⚡ Opportunities'!F:F,TRUE,'⚡ Opportunities'!G:G,TRUE) -> 71 | AT19: =SUMIFS('⚡ Opportunities'!H:H,'⚡ Opportunities'!C:C,">="&AA19,'⚡ Opportunities'!C:C,"<"&EDATE(AA19,1),'⚡ Opportunities'!F:F,TRUE,'⚡ Opportunities'!G:G,TRUE) -> 100590
R20: 46539 | S20: 90.186249 | T20: 119.95411 | U20: 112.00513 | V20: 61.927094 | W20: 99578.494 | X20: 1794372.4 | Y20: $100k | AA20: =EDATE(AA21,-1) -> 45809 | AB20: =COUNTIFS('⚡ Leads'!D:D,">="&AA20,'⚡ Leads'!D:D,"<"&EDATE(AA20,1)) -> 97 | AC20: =COUNTIFS('⚡ Events'!C:C,">="&AA20,'⚡ Events'!C:C,"<"&EDATE(AA20,1)) -> 129 | AD20: =COUNTIFS('⚡ Opportunities'!C:C,">="&AA20,'⚡ Opportunities'!C:C,"<"&EDATE(AA20,1)) -> 122 | AE20: =COUNTIFS('⚡ Opportunities'!C:C,">="&AA20,'⚡ Opportunities'!C:C,"<"&EDATE(AA20,1),'⚡ Opportunities'!F:F,TRUE,'⚡ Opportunities'!G:G,TRUE) -> 65 | AF20: =SUMIFS('⚡ Opportunities'!H:H,'⚡ Opportunities'!C:C,">="&AA20,'⚡ Opportunities'!C:C,"<"&EDATE(AA20,1),'⚡ Opportunities'!F:F,TRUE,'⚡ Opportunities'!G:G,TRUE) -> 98170 | AH20: =EDATE(AH21,-1) -> 45809 | AI20: =COUNTIFS('⚡ Leads'!D:D,">="&AA20,'⚡ Leads'!D:D,"<"&EDATE(AA20,1)) -> 97 | AJ20: =COUNTIFS('⚡ Events'!C:C,">="&AA20,'⚡ Events'!C:C,"<"&EDATE(AA20,1)) -> 129 | AK20: =COUNTIFS('⚡ Opportunities'!C:C,">="&AA20,'⚡ Opportunities'!C:C,"<"&EDATE(AA20,1)) -> 122 | AL20: =COUNTIFS('⚡ Opportunities'!C:C,">="&AA20,'⚡ Opportunities'!C:C,"<"&EDATE(AA20,1),'⚡ Opportunities'!F:F,TRUE,'⚡ Opportunities'!G:G,TRUE) -> 65 | AM20: =SUMIFS('⚡ Opportunities'!H:H,'⚡ Opportunities'!C:C,">="&AA20,'⚡ Opportunities'!C:C,"<"&EDATE(AA20,1),'⚡ Opportunities'!F:F,TRUE,'⚡ Opportunities'!G:G,TRUE) -> 98170 | AO20: =EDATE(AO21,-1) -> 45748 | AP20: =IFERROR(AP19*$G$6+(1-$G$6)*AVERAGE(AP3:AP19),"") -> 95.282353 | AQ20: =IFERROR(AQ19*$G$6+(1-$G$6)*AVERAGE(AQ3:AQ19),"") -> 125.64706 | AR20: =IFERROR(AR19*$G$6+(1-$G$6)*AVERAGE(AR3:AR19),"") -> 118.35294 | AS20: =IFERROR(AS19*$G$6+(1-$G$6)*AVERAGE(AS3:AS19),"") -> 67.564706 | AT20: =IFERROR(AT19*$G$6+(1-$G$6)*AVERAGE(AT3:AT19),"") -> 98775.765
B21: New Forecasted Revenue | D21: {=TRANSPOSE(W3:X14)} -> 99793.517 | E21: 99950.892 | F21: 99972.213 | G21: 100038.59 | H21: 99437.794 | I21: 99384.072 | J21: 99638.671 | K21: 99836.217 | L21: 100041.74 | M21: 99855.707 | N21: 99698.242 | O21: 99583.123 | R21: 46569 | S21: 90.196489 | T21: 119.96963 | U21: 112.01863 | V21: 61.918351 | W21: 99599.018 | X21: 1893971.4 | Y21: $100k | AA21: =EDATE(AA22,-1) -> 45839 | AB21: =COUNTIFS('⚡ Leads'!D:D,">="&AA21,'⚡ Leads'!D:D,"<"&EDATE(AA21,1)) -> 101 | AC21: =COUNTIFS('⚡ Events'!C:C,">="&AA21,'⚡ Events'!C:C,"<"&EDATE(AA21,1)) -> 131 | AD21: =COUNTIFS('⚡ Opportunities'!C:C,">="&AA21,'⚡ Opportunities'!C:C,"<"&EDATE(AA21,1)) -> 126 | AE21: =COUNTIFS('⚡ Opportunities'!C:C,">="&AA21,'⚡ Opportunities'!C:C,"<"&EDATE(AA21,1),'⚡ Opportunities'!F:F,TRUE,'⚡ Opportunities'!G:G,TRUE) -> 65 | AF21: =SUMIFS('⚡ Opportunities'!H:H,'⚡ Opportunities'!C:C,">="&AA21,'⚡ Opportunities'!C:C,"<"&EDATE(AA21,1),'⚡ Opportunities'!F:F,TRUE,'⚡ Opportunities'!G:G,TRUE) -> 107140 | AH21: =EDATE(AH22,-1) -> 45839 | AI21: =COUNTIFS('⚡ Leads'!D:D,">="&AA21,'⚡ Leads'!D:D,"<"&EDATE(AA21,1)) -> 101 | AJ21: =COUNTIFS('⚡ Events'!C:C,">="&AA21,'⚡ Events'!C:C,"<"&EDATE(AA21,1)) -> 131 | AK21: =COUNTIFS('⚡ Opportunities'!C:C,">="&AA21,'⚡ Opportunities'!C:C,"<"&EDATE(AA21,1)) -> 126 | AL21: =COUNTIFS('⚡ Opportunities'!C:C,">="&AA21,'⚡ Opportunities'!C:C,"<"&EDATE(AA21,1),'⚡ Opportunities'!F:F,TRUE,'⚡ Opportunities'!G:G,TRUE) -> 65 | AM21: =SUMIFS('⚡ Opportunities'!H:H,'⚡ Opportunities'!C:C,">="&AA21,'⚡ Opportunities'!C:C,"<"&EDATE(AA21,1),'⚡ Opportunities'!F:F,TRUE,'⚡ Opportunities'!G:G,TRUE) -> 107140 | AO21: =EDATE(AO22,-1) -> 45778 | AP21: =IFERROR(AP20*$G$6+(1-$G$6)*AVERAGE(AP4:AP20),"") -> 92.723322 | AQ21: =IFERROR(AQ20*$G$6+(1-$G$6)*AVERAGE(AQ4:AQ20),"") -> 122.66644 | AR21: =IFERROR(AR20*$G$6+(1-$G$6)*AVERAGE(AR4:AR20),"") -> 115.15709 | AS21: =IFERROR(AS20*$G$6+(1-$G$6)*AVERAGE(AS4:AS20),"") -> 65.117232 | AT21: =IFERROR(AT20*$G$6+(1-$G$6)*AVERAGE(AT4:AT20),"") -> 97649.15
B22: Total Forecast Revenue | D22: 99793.517 | E22: 199744.41 | F22: 299716.62 | G22: 399755.21 | H22: 499193.01 | I22: 598577.08 | J22: 698215.75 | K22: 798051.97 | L22: 898093.71 | M22: 997949.41 | N22: 1097647.7 | O22: 1197230.8 | R22: 46600 | S22: 90.216996 | T22: 119.99679 | U22: 112.04605 | V22: 61.91989 | W22: 99611.297 | X22: 1993582.7 | Y22: $100k | AA22: =EDATE(AA23,-1) -> 45870 | AB22: =COUNTIFS('⚡ Leads'!D:D,">="&AA22,'⚡ Leads'!D:D,"<"&EDATE(AA22,1)) -> 104 | AC22: =COUNTIFS('⚡ Events'!C:C,">="&AA22,'⚡ Events'!C:C,"<"&EDATE(AA22,1)) -> 135 | AD22: =COUNTIFS('⚡ Opportunities'!C:C,">="&AA22,'⚡ Opportunities'!C:C,"<"&EDATE(AA22,1)) -> 130 | AE22: =COUNTIFS('⚡ Opportunities'!C:C,">="&AA22,'⚡ Opportunities'!C:C,"<"&EDATE(AA22,1),'⚡ Opportunities'!F:F,TRUE,'⚡ Opportunities'!G:G,TRUE) -> 69 | AF22: =SUMIFS('⚡ Opportunities'!H:H,'⚡ Opportunities'!C:C,">="&AA22,'⚡ Opportunities'!C:C,"<"&EDATE(AA22,1),'⚡ Opportunities'!F:F,TRUE,'⚡ Opportunities'!G:G,TRUE) -> 90170 | AH22: =EDATE(AH23,-1) -> 45870 | AI22: =COUNTIFS('⚡ Leads'!D:D,">="&AA22,'⚡ Leads'!D:D,"<"&EDATE(AA22,1)) -> 104 | AJ22: =COUNTIFS('⚡ Events'!C:C,">="&AA22,'⚡ Events'!C:C,"<"&EDATE(AA22,1)) -> 135 | AK22: =COUNTIFS('⚡ Opportunities'!C:C,">="&AA22,'⚡ Opportunities'!C:C,"<"&EDATE(AA22,1)) -> 130 | AL22: =COUNTIFS('⚡ Opportunities'!C:C,">="&AA22,'⚡ Opportunities'!C:C,"<"&EDATE(AA22,1),'⚡ Opportunities'!F:F,TRUE,'⚡ Opportunities'!G:G,TRUE) -> 69 | AM22: =SUMIFS('⚡ Opportunities'!H:H,'⚡ Opportunities'!C:C,">="&AA22,'⚡ Opportunities'!C:C,"<"&EDATE(AA22,1),'⚡ Opportunities'!F:F,TRUE,'⚡ Opportunities'!G:G,TRUE) -> 90170 | AO22: =EDATE(AO23,-1) -> 45809 | AP22: =IFERROR(AP21*$G$6+(1-$G$6)*AVERAGE(AP5:AP21),"") -> 91.025783 | AQ22: =IFERROR(AQ21*$G$6+(1-$G$6)*AVERAGE(AQ5:AQ21),"") -> 120.71331 | AR22: =IFERROR(AR21*$G$6+(1-$G$6)*AVERAGE(AR5:AR21),"") -> 113.01403 | AS22: =IFERROR(AS21*$G$6+(1-$G$6)*AVERAGE(AS5:AS21),"") -> 63.454749 | AT22: =IFERROR(AT21*$G$6+(1-$G$6)*AVERAGE(AT5:AT21),"") -> 97061.849
R23: 46631 | S23: 90.242809 | T23: 120.02957 | U23: 112.08087 | V23: 61.929784 | W23: 99616.874 | X23: 2093199.6 | Y23: $100k | AA23: =EDATE(AA24,-1) -> 45901 | AB23: =COUNTIFS('⚡ Leads'!D:D,">="&AA23,'⚡ Leads'!D:D,"<"&EDATE(AA23,1)) -> 102 | AC23: =COUNTIFS('⚡ Events'!C:C,">="&AA23,'⚡ Events'!C:C,"<"&EDATE(AA23,1)) -> 133 | AD23: =COUNTIFS('⚡ Opportunities'!C:C,">="&AA23,'⚡ Opportunities'!C:C,"<"&EDATE(AA23,1)) -> 127 | AE23: =COUNTIFS('⚡ Opportunities'!C:C,">="&AA23,'⚡ Opportunities'!C:C,"<"&EDATE(AA23,1),'⚡ Opportunities'!F:F,TRUE,'⚡ Opportunities'!G:G,TRUE) -> 70 | AF23: =SUMIFS('⚡ Opportunities'!H:H,'⚡ Opportunities'!C:C,">="&AA23,'⚡ Opportunities'!C:C,"<"&EDATE(AA23,1),'⚡ Opportunities'!F:F,TRUE,'⚡ Opportunities'!G:G,TRUE) -> 108190 | AH23: =EDATE(AH24,-1) -> 45901 | AI23: =COUNTIFS('⚡ Leads'!D:D,">="&AA23,'⚡ Leads'!D:D,"<"&EDATE(AA23,1)) -> 102 | AJ23: =COUNTIFS('⚡ Events'!C:C,">="&AA23,'⚡ Events'!C:C,"<"&EDATE(AA23,1)) -> 133 | AK23: =COUNTIFS('⚡ Opportunities'!C:C,">="&AA23,'⚡ Opportunities'!C:C,"<"&EDATE(AA23,1)) -> 127 | AL23: =COUNTIFS('⚡ Opportunities'!C:C,">="&AA23,'⚡ Opportunities'!C:C,"<"&EDATE(AA23,1),'⚡ Opportunities'!F:F,TRUE,'⚡ Opportunities'!G:G,TRUE) -> 70 | AM23: =SUMIFS('⚡ Opportunities'!H:H,'⚡ Opportunities'!C:C,">="&AA23,'⚡ Opportunities'!C:C,"<"&EDATE(AA23,1),'⚡ Opportunities'!F:F,TRUE,'⚡ Opportunities'!G:G,TRUE) -> 108190 | AO23: =EDATE(AO24,-1) -> 45839 | AP23: =IFERROR(AP22*$G$6+(1-$G$6)*AVERAGE(AP6:AP22),"") -> 89.950408 | AQ23: =IFERROR(AQ22*$G$6+(1-$G$6)*AVERAGE(AQ6:AQ22),"") -> 119.47684 | AR23: =IFERROR(AR22*$G$6+(1-$G$6)*AVERAGE(AR6:AR22),"") -> 111.64092 | AS23: =IFERROR(AS22*$G$6+(1-$G$6)*AVERAGE(AS6:AS22),"") -> 62.353643 | AT23: =IFERROR(AT22*$G$6+(1-$G$6)*AVERAGE(AT6:AT22),"") -> 97149.911
R24: 46661 | S24: 90.269625 | T24: 120.06291 | U24: 112.11736 | V24: 61.94516 | W24: 99616.374 | X24: 2192816 | Y24: $100k | AA24: =EDATE(AA25,-1) -> 45931 | AB24: =COUNTIFS('⚡ Leads'!D:D,">="&AA24,'⚡ Leads'!D:D,"<"&EDATE(AA24,1)) -> 107 | AC24: =COUNTIFS('⚡ Events'!C:C,">="&AA24,'⚡ Events'!C:C,"<"&EDATE(AA24,1)) -> 137 | AD24: =COUNTIFS('⚡ Opportunities'!C:C,">="&AA24,'⚡ Opportunities'!C:C,"<"&EDATE(AA24,1)) -> 133 | AE24: =COUNTIFS('⚡ Opportunities'!C:C,">="&AA24,'⚡ Opportunities'!C:C,"<"&EDATE(AA24,1),'⚡ Opportunities'!F:F,TRUE,'⚡ Opportunities'!G:G,TRUE) -> 72 | AF24: =SUMIFS('⚡ Opportunities'!H:H,'⚡ Opportunities'!C:C,">="&AA24,'⚡ Opportunities'!C:C,"<"&EDATE(AA24,1),'⚡ Opportunities'!F:F,TRUE,'⚡ Opportunities'!G:G,TRUE) -> 153340 | AH24: =EDATE(AH25,-1) -> 45931 | AI24: =COUNTIFS('⚡ Leads'!D:D,">="&AA24,'⚡ Leads'!D:D,"<"&EDATE(AA24,1)) -> 107 | AJ24: =COUNTIFS('⚡ Events'!C:C,">="&AA24,'⚡ Events'!C:C,"<"&EDATE(AA24,1)) -> 137 | AK24: =COUNTIFS('⚡ Opportunities'!C:C,">="&AA24,'⚡ Opportunities'!C:C,"<"&EDATE(AA24,1)) -> 133 | AL24: =COUNTIFS('⚡ Opportunities'!C:C,">="&AA24,'⚡ Opportunities'!C:C,"<"&EDATE(AA24,1),'⚡ Opportunities'!F:F,TRUE,'⚡ Opportunities'!G:G,TRUE) -> 72 | AM24: =SUMIFS('⚡ Opportunities'!H:H,'⚡ Opportunities'!C:C,">="&AA24,'⚡ Opportunities'!C:C,"<"&EDATE(AA24,1),'⚡ Opportunities'!F:F,TRUE,'⚡ Opportunities'!G:G,TRUE) -> 153340 | AO24: =EDATE(AO25,-1) -> 45870 | AP24: =IFERROR(AP23*$G$6+(1-$G$6)*AVERAGE(AP7:AP23),"") -> 89.313054 | AQ24: =IFERROR(AQ23*$G$6+(1-$G$6)*AVERAGE(AQ7:AQ23),"") -> 118.75211 | AR24: =IFERROR(AR23*$G$6+(1-$G$6)*AVERAGE(AR7:AR23),"") -> 110.84409 | AS24: =IFERROR(AS23*$G$6+(1-$G$6)*AVERAGE(AS7:AS23),"") -> 61.747506 | AT24: =IFERROR(AT23*$G$6+(1-$G$6)*AVERAGE(AT7:AT23),"") -> 97718.596
B25: 24-Month Sales Forecast | R25: 46692 | S25: 90.294208 | T25: 120.09287 | U25: 112.15104 | V25: 61.963867 | W25: 99618.075 | X25: 2292434 | Y25: $100k | AA25: =EDATE(AA26,-1) -> 45962 | AB25: =COUNTIFS('⚡ Leads'!D:D,">="&AA25,'⚡ Leads'!D:D,"<"&EDATE(AA25,1)) -> 108 | AC25: =COUNTIFS('⚡ Events'!C:C,">="&AA25,'⚡ Events'!C:C,"<"&EDATE(AA25,1)) -> 138 | AD25: =COUNTIFS('⚡ Opportunities'!C:C,">="&AA25,'⚡ Opportunities'!C:C,"<"&EDATE(AA25,1)) -> 136 | AE25: =COUNTIFS('⚡ Opportunities'!C:C,">="&AA25,'⚡ Opportunities'!C:C,"<"&EDATE(AA25,1),'⚡ Opportunities'!F:F,TRUE,'⚡ Opportunities'!G:G,TRUE) -> 61 | AF25: =SUMIFS('⚡ Opportunities'!H:H,'⚡ Opportunities'!C:C,">="&AA25,'⚡ Opportunities'!C:C,"<"&EDATE(AA25,1),'⚡ Opportunities'!F:F,TRUE,'⚡ Opportunities'!G:G,TRUE) -> 113700 | AH25: =EDATE(AH26,-1) -> 45962 | AI25: =COUNTIFS('⚡ Leads'!D:D,">="&AA25,'⚡ Leads'!D:D,"<"&EDATE(AA25,1)) -> 108 | AJ25: =COUNTIFS('⚡ Events'!C:C,">="&AA25,'⚡ Events'!C:C,"<"&EDATE(AA25,1)) -> 138 | AK25: =COUNTIFS('⚡ Opportunities'!C:C,">="&AA25,'⚡ Opportunities'!C:C,"<"&EDATE(AA25,1)) -> 136 | AL25: =COUNTIFS('⚡ Opportunities'!C:C,">="&AA25,'⚡ Opportunities'!C:C,"<"&EDATE(AA25,1),'⚡ Opportunities'!F:F,TRUE,'⚡ Opportunities'!G:G,TRUE) -> 61 | AM25: =SUMIFS('⚡ Opportunities'!H:H,'⚡ Opportunities'!C:C,">="&AA25,'⚡ Opportunities'!C:C,"<"&EDATE(AA25,1),'⚡ Opportunities'!F:F,TRUE,'⚡ Opportunities'!G:G,TRUE) -> 113700 | AO25: =EDATE(AO26,-1) -> 45901 | AP25: =IFERROR(AP24*$G$6+(1-$G$6)*AVERAGE(AP8:AP24),"") -> 88.97156 | AQ25: =IFERROR(AQ24*$G$6+(1-$G$6)*AVERAGE(AQ8:AQ24),"") -> 118.39293 | AR25: =IFERROR(AR24*$G$6+(1-$G$6)*AVERAGE(AR8:AR24),"") -> 110.41655 | AS25: =IFERROR(AS24*$G$6+(1-$G$6)*AVERAGE(AS8:AS24),"") -> 61.494921 | AT25: =IFERROR(AT24*$G$6+(1-$G$6)*AVERAGE(AT8:AT24),"") -> 98683.762
R26: 46722 | S26: 90.314197 | T26: 120.11686 | U26: 112.17853 | V26: 61.982614 | W26: 99622.189 | X26: 2392056.2 | Y26: $100k | AA26: =EDATE(AA27,-1) -> 45992 | AB26: =COUNTIFS('⚡ Leads'!D:D,">="&AA26,'⚡ Leads'!D:D,"<"&EDATE(AA26,1)) -> 112 | AC26: =COUNTIFS('⚡ Events'!C:C,">="&AA26,'⚡ Events'!C:C,"<"&EDATE(AA26,1)) -> 143 | AD26: =COUNTIFS('⚡ Opportunities'!C:C,">="&AA26,'⚡ Opportunities'!C:C,"<"&EDATE(AA26,1)) -> 140 | AE26: =COUNTIFS('⚡ Opportunities'!C:C,">="&AA26,'⚡ Opportunities'!C:C,"<"&EDATE(AA26,1),'⚡ Opportunities'!F:F,TRUE,'⚡ Opportunities'!G:G,TRUE) -> 77 | AF26: =SUMIFS('⚡ Opportunities'!H:H,'⚡ Opportunities'!C:C,">="&AA26,'⚡ Opportunities'!C:C,"<"&EDATE(AA26,1),'⚡ Opportunities'!F:F,TRUE,'⚡ Opportunities'!G:G,TRUE) -> 131910 | AH26: =EDATE(AH27,-1) -> 45992 | AI26: =COUNTIFS('⚡ Leads'!D:D,">="&AA26,'⚡ Leads'!D:D,"<"&EDATE(AA26,1)) -> 112 | AJ26: =COUNTIFS('⚡ Events'!C:C,">="&AA26,'⚡ Events'!C:C,"<"&EDATE(AA26,1)) -> 143 | AK26: =COUNTIFS('⚡ Opportunities'!C:C,">="&AA26,'⚡ Opportunities'!C:C,"<"&EDATE(AA26,1)) -> 140 | AL26: =COUNTIFS('⚡ Opportunities'!C:C,">="&AA26,'⚡ Opportunities'!C:C,"<"&EDATE(AA26,1),'⚡ Opportunities'!F:F,TRUE,'⚡ Opportunities'!G:G,TRUE) -> 77 | AM26: =SUMIFS('⚡ Opportunities'!H:H,'⚡ Opportunities'!C:C,">="&AA26,'⚡ Opportunities'!C:C,"<"&EDATE(AA26,1),'⚡ Opportunities'!F:F,TRUE,'⚡ Opportunities'!G:G,TRUE) -> 131910 | AO26: =EDATE(AO27,-1) -> 45931 | AP26: =IFERROR(AP25*$G$6+(1-$G$6)*AVERAGE(AP9:AP25),"") -> 88.89803 | AQ26: =IFERROR(AQ25*$G$6+(1-$G$6)*AVERAGE(AQ9:AQ25),"") -> 118.3455 | AR26: =IFERROR(AR25*$G$6+(1-$G$6)*AVERAGE(AR9:AR25),"") -> 110.31472 | AS26: =IFERROR(AS25*$G$6+(1-$G$6)*AVERAGE(AS9:AS25),"") -> 61.31044 | AT26: =IFERROR(AT25*$G$6+(1-$G$6)*AVERAGE(AT9:AT25),"") -> 99174.057
AA27: =D14 -> 46023 | AB27: =_xlfn.FORECAST.LINEAR($AA27,AB$3:AB26,$AA$3:$AA26) -> 113.68632 | AC27: =_xlfn.FORECAST.LINEAR($AA27,AC$3:AC26,$AA$3:$AA26) -> 146.57513 | AD27: =_xlfn.FORECAST.LINEAR($AA27,AD$3:AD26,$AA$3:$AA26) -> 142.17011 | AE27: =_xlfn.FORECAST.LINEAR($AA27,AE$3:AE26,$AA$3:$AA26) -> 74.829846 | AF27: =_xlfn.FORECAST.LINEAR($AA27,AF$3:AF26,$AA$3:$AA26) -> 127961.34 | AH27: =D14 -> 46023 | AI27: =IFERROR(AVERAGE(OFFSET(AI26,-$I$6+1,0,$I$6,1)),"") -> 100 | AJ27: =IFERROR(AVERAGE(OFFSET(AJ26,-$I$6+1,0,$I$6,1)),"") -> 130.75 | AK27: =IFERROR(AVERAGE(OFFSET(AK26,-$I$6+1,0,$I$6,1)),"") -> 125 | AL27: =IFERROR(AVERAGE(OFFSET(AL26,-$I$6+1,0,$I$6,1)),"") -> 66.166667 | AM27: =IFERROR(AVERAGE(OFFSET(AM26,-$I$6+1,0,$I$6,1)),"") -> 108590.83 | AO27: =K14 -> 45962 | AP27: =IFERROR(AP26*$G$6+(1-$G$6)*AVERAGE(AP10:AP26),"") -> 88.979183 | AQ27: =IFERROR(AQ26*$G$6+(1-$G$6)*AVERAGE(AQ10:AQ26),"") -> 118.47633 | AR27: =IFERROR(AR26*$G$6+(1-$G$6)*AVERAGE(AR10:AR26),"") -> 110.40166 | AS27: =IFERROR(AS26*$G$6+(1-$G$6)*AVERAGE(AS10:AS26),"") -> 61.237095 | AT27: =IFERROR(AT26*$G$6+(1-$G$6)*AVERAGE(AT10:AT26),"") -> 99793.517
AA28: {=IFERROR(_xlfn.BYROW(_xlfn.SEQUENCE(23),_xlfn.LAMBDA(_xlpm.x,IFERROR(DATE(YEAR(AA27),MONTH(AA27)+_xlpm.x,1),"Month "&(_xlpm.x+1)))),"")} -> 46054 | AB28: =_xlfn.FORECAST.LINEAR($AA28,AB$3:AB27,$AA$3:$AA27) -> 115.82328 | AC28: =_xlfn.FORECAST.LINEAR($AA28,AC$3:AC27,$AA$3:$AA27) -> 149.05555 | AD28: =_xlfn.FORECAST.LINEAR($AA28,AD$3:AD27,$AA$3:$AA27) -> 144.88874 | AE28: =_xlfn.FORECAST.LINEAR($AA28,AE$3:AE27,$AA$3:$AA27) -> 76.192125 | AF28: =_xlfn.FORECAST.LINEAR($AA28,AF$3:AF27,$AA$3:$AA27) -> 130376.77 | AH28: {=IFERROR(_xlfn.BYROW(_xlfn.SEQUENCE(23),_xlfn.LAMBDA(_xlpm.x,IFERROR(DATE(YEAR(AH27),MONTH(AH27)+_xlpm.x,1),"Month "&(_xlpm.x+1)))),"")} -> 46054 | AI28: =IFERROR(AVERAGE(OFFSET(AI27,-$I$6+1,0,$I$6,1)),"") -> 100.83333 | AJ28: =IFERROR(AVERAGE(OFFSET(AJ27,-$I$6+1,0,$I$6,1)),"") -> 131.72917 | AK28: =IFERROR(AVERAGE(OFFSET(AK27,-$I$6+1,0,$I$6,1)),"") -> 126.16667 | AL28: =IFERROR(AVERAGE(OFFSET(AL27,-$I$6+1,0,$I$6,1)),"") -> 67.013889 | AM28: =IFERROR(AVERAGE(OFFSET(AM27,-$I$6+1,0,$I$6,1)),"") -> 111465.9 | AO28: {=IFERROR(_xlfn.BYROW(_xlfn.SEQUENCE(23),_xlfn.LAMBDA(_xlpm.x,IFERROR(DATE(YEAR(AO27),MONTH(AO27)+_xlpm.x,1),"Month "&(_xlpm.x+1)))),"")} -> 45992 | AP28: =IFERROR(AP27*$G$6+(1-$G$6)*AVERAGE(AP11:AP27),"") -> 89.149743 | AQ28: =IFERROR(AQ27*$G$6+(1-$G$6)*AVERAGE(AQ11:AQ27),"") -> 118.71602 | AR28: =IFERROR(AR27*$G$6+(1-$G$6)*AVERAGE(AR11:AR27),"") -> 110.60535 | AS28: =IFERROR(AS27*$G$6+(1-$G$6)*AVERAGE(AS11:AS27),"") -> 61.192974 | AT28: =IFERROR(AT27*$G$6+(1-$G$6)*AVERAGE(AT11:AT27),"") -> 99950.892
AA29: 46082 | AB29: =_xlfn.FORECAST.LINEAR($AA29,AB$3:AB28,$AA$3:$AA28) -> 117.75343 | AC29: =_xlfn.FORECAST.LINEAR($AA29,AC$3:AC28,$AA$3:$AA28) -> 151.29592 | AD29: =_xlfn.FORECAST.LINEAR($AA29,AD$3:AD28,$AA$3:$AA28) -> 147.34427 | AE29: =_xlfn.FORECAST.LINEAR($AA29,AE$3:AE28,$AA$3:$AA28) -> 77.422571 | AF29: =_xlfn.FORECAST.LINEAR($AA29,AF$3:AF28,$AA$3:$AA28) -> 132558.46 | AH29: 46082 | AI29: =IFERROR(AVERAGE(OFFSET(AI28,-$I$6+1,0,$I$6,1)),"") -> 101.56944 | AJ29: =IFERROR(AVERAGE(OFFSET(AJ28,-$I$6+1,0,$I$6,1)),"") -> 132.62326 | AK29: =IFERROR(AVERAGE(OFFSET(AK28,-$I$6+1,0,$I$6,1)),"") -> 127.18056 | AL29: =IFERROR(AVERAGE(OFFSET(AL28,-$I$6+1,0,$I$6,1)),"") -> 67.015046 | AM29: =IFERROR(AVERAGE(OFFSET(AM28,-$I$6+1,0,$I$6,1)),"") -> 112408.06 | AO29: 46023 | AP29: =IFERROR(AP28*$G$6+(1-$G$6)*AVERAGE(AP12:AP28),"") -> 89.417364 | AQ29: =IFERROR(AQ28*$G$6+(1-$G$6)*AVERAGE(AQ12:AQ28),"") -> 119.05736 | AR29: =IFERROR(AR28*$G$6+(1-$G$6)*AVERAGE(AR12:AR28),"") -> 110.9519 | AS29: =IFERROR(AS28*$G$6+(1-$G$6)*AVERAGE(AS12:AS28),"") -> 61.183476 | AT29: =IFERROR(AT28*$G$6+(1-$G$6)*AVERAGE(AT12:AT28),"") -> 99972.213
AA30: 46113 | AB30: =_xlfn.FORECAST.LINEAR($AA30,AB$3:AB29,$AA$3:$AA29) -> 119.89039 | AC30: =_xlfn.FORECAST.LINEAR($AA30,AC$3:AC29,$AA$3:$AA29) -> 153.77634 | AD30: =_xlfn.FORECAST.LINEAR($AA30,AD$3:AD29,$AA$3:$AA29) -> 150.0629 | AE30: =_xlfn.FORECAST.LINEAR($AA30,AE$3:AE29,$AA$3:$AA29) -> 78.78485 | AF30: =_xlfn.FORECAST.LINEAR($AA30,AF$3:AF29,$AA$3:$AA29) -> 134973.9 | AH30: 46113 | AI30: =IFERROR(AVERAGE(OFFSET(AI29,-$I$6+1,0,$I$6,1)),"") -> 102.28356 | AJ30: =IFERROR(AVERAGE(OFFSET(AJ29,-$I$6+1,0,$I$6,1)),"") -> 133.25854 | AK30: =IFERROR(AVERAGE(OFFSET(AK29,-$I$6+1,0,$I$6,1)),"") -> 128.02894 | AL30: =IFERROR(AVERAGE(OFFSET(AL29,-$I$6+1,0,$I$6,1)),"") -> 67.7663 | AM30: =IFERROR(AVERAGE(OFFSET(AM29,-$I$6+1,0,$I$6,1)),"") -> 113792.07 | AO30: 46054 | AP30: =IFERROR(AP29*$G$6+(1-$G$6)*AVERAGE(AP13:AP29),"") -> 89.718724 | AQ30: =IFERROR(AQ29*$G$6+(1-$G$6)*AVERAGE(AQ13:AQ29),"") -> 119.42523 | AR30: =IFERROR(AR29*$G$6+(1-$G$6)*AVERAGE(AR13:AR29),"") -> 111.34622 | AS30: =IFERROR(AS29*$G$6+(1-$G$6)*AVERAGE(AS13:AS29),"") -> 61.295684 | AT30: =IFERROR(AT29*$G$6+(1-$G$6)*AVERAGE(AT13:AT29),"") -> 100038.59
AA31: 46143 | AB31: =_xlfn.FORECAST.LINEAR($AA31,AB$3:AB30,$AA$3:$AA30) -> 121.95841 | AC31: =_xlfn.FORECAST.LINEAR($AA31,AC$3:AC30,$AA$3:$AA30) -> 156.17674 | AD31: =_xlfn.FORECAST.LINEAR($AA31,AD$3:AD30,$AA$3:$AA30) -> 152.69383 | AE31: =_xlfn.FORECAST.LINEAR($AA31,AE$3:AE30,$AA$3:$AA30) -> 80.103185 | AF31: =_xlfn.FORECAST.LINEAR($AA31,AF$3:AF30,$AA$3:$AA30) -> 137311.42 | AH31: 46143 | AI31: =IFERROR(AVERAGE(OFFSET(AI30,-$I$6+1,0,$I$6,1)),"") -> 102.89053 | AJ31: =IFERROR(AVERAGE(OFFSET(AJ30,-$I$6+1,0,$I$6,1)),"") -> 133.69675 | AK31: =IFERROR(AVERAGE(OFFSET(AK30,-$I$6+1,0,$I$6,1)),"") -> 128.61468 | AL31: =IFERROR(AVERAGE(OFFSET(AL30,-$I$6+1,0,$I$6,1)),"") -> 68.163492 | AM31: =IFERROR(AVERAGE(OFFSET(AM30,-$I$6+1,0,$I$6,1)),"") -> 112455.57 | AO31: 46082 | AP31: =IFERROR(AP30*$G$6+(1-$G$6)*AVERAGE(AP14:AP30),"") -> 90.003562 | AQ31: =IFERROR(AQ30*$G$6+(1-$G$6)*AVERAGE(AQ14:AQ30),"") -> 119.78335 | AR31: =IFERROR(AR30*$G$6+(1-$G$6)*AVERAGE(AR14:AR30),"") -> 111.73633 | AS31: =IFERROR(AS30*$G$6+(1-$G$6)*AVERAGE(AS14:AS30),"") -> 61.400693 | AT31: =IFERROR(AT30*$G$6+(1-$G$6)*AVERAGE(AT14:AT30),"") -> 99437.794
AA32: 46174 | AB32: =_xlfn.FORECAST.LINEAR($AA32,AB$3:AB31,$AA$3:$AA31) -> 124.09537 | AC32: =_xlfn.FORECAST.LINEAR($AA32,AC$3:AC31,$AA$3:$AA31) -> 158.65716 | AD32: =_xlfn.FORECAST.LINEAR($AA32,AD$3:AD31,$AA$3:$AA31) -> 155.41246 | AE32: =_xlfn.FORECAST.LINEAR($AA32,AE$3:AE31,$AA$3:$AA31) -> 81.465464 | AF32: =_xlfn.FORECAST.LINEAR($AA32,AF$3:AF31,$AA$3:$AA31) -> 139726.85 | AH32: 46174 | AI32: =IFERROR(AVERAGE(OFFSET(AI31,-$I$6+1,0,$I$6,1)),"") -> 103.21474 | AJ32: =IFERROR(AVERAGE(OFFSET(AJ31,-$I$6+1,0,$I$6,1)),"") -> 134.00481 | AK32: =IFERROR(AVERAGE(OFFSET(AK31,-$I$6+1,0,$I$6,1)),"") -> 129.08257 | AL32: =IFERROR(AVERAGE(OFFSET(AL31,-$I$6+1,0,$I$6,1)),"") -> 67.927116 | AM32: =IFERROR(AVERAGE(OFFSET(AM31,-$I$6+1,0,$I$6,1)),"") -> 113444.37 | AO32: 46113 | AP32: =IFERROR(AP31*$G$6+(1-$G$6)*AVERAGE(AP15:AP31),"") -> 90.266768 | AQ32: =IFERROR(AQ31*$G$6+(1-$G$6)*AVERAGE(AQ15:AQ31),"") -> 120.09083 | AR32: =IFERROR(AR31*$G$6+(1-$G$6)*AVERAGE(AR15:AR31),"") -> 112.10414 | AS32: =IFERROR(AS31*$G$6+(1-$G$6)*AVERAGE(AS15:AS31),"") -> 61.642356 | AT32: =IFERROR(AT31*$G$6+(1-$G$6)*AVERAGE(AT15:AT31),"") -> 99384.072
AA33: 46204 | AB33: =_xlfn.FORECAST.LINEAR($AA33,AB$3:AB32,$AA$3:$AA32) -> 126.1634 | AC33: =_xlfn.FORECAST.LINEAR($AA33,AC$3:AC32,$AA$3:$AA32) -> 161.05757 | AD33: =_xlfn.FORECAST.LINEAR($AA33,AD$3:AD32,$AA$3:$AA32) -> 158.04339 | AE33: =_xlfn.FORECAST.LINEAR($AA33,AE$3:AE32,$AA$3:$AA32) -> 82.783798 | AF33: =_xlfn.FORECAST.LINEAR($AA33,AF$3:AF32,$AA$3:$AA32) -> 142064.38 | AH33: 46204 | AI33: =IFERROR(AVERAGE(OFFSET(AI32,-$I$6+1,0,$I$6,1)),"") -> 103.73263 | AJ33: =IFERROR(AVERAGE(OFFSET(AJ32,-$I$6+1,0,$I$6,1)),"") -> 134.42188 | AK33: =IFERROR(AVERAGE(OFFSET(AK32,-$I$6+1,0,$I$6,1)),"") -> 129.67278 | AL33: =IFERROR(AVERAGE(OFFSET(AL32,-$I$6+1,0,$I$6,1)),"") -> 68.171042 | AM33: =IFERROR(AVERAGE(OFFSET(AM32,-$I$6+1,0,$I$6,1)),"") -> 114717.23 | AO33: 46143 | AP33: =IFERROR(AP32*$G$6+(1-$G$6)*AVERAGE(AP16:AP32),"") -> 90.480472 | AQ33: =IFERROR(AQ32*$G$6+(1-$G$6)*AVERAGE(AQ16:AQ32),"") -> 120.34964 | AR33: =IFERROR(AR32*$G$6+(1-$G$6)*AVERAGE(AR16:AR32),"") -> 112.41139 | AS33: =IFERROR(AS32*$G$6+(1-$G$6)*AVERAGE(AS16:AS32),"") -> 61.902067 | AT33: =IFERROR(AT32*$G$6+(1-$G$6)*AVERAGE(AT16:AT32),"") -> 99638.671
AA34: 46235 | AB34: =_xlfn.FORECAST.LINEAR($AA34,AB$3:AB33,$AA$3:$AA33) -> 128.30035 | AC34: =_xlfn.FORECAST.LINEAR($AA34,AC$3:AC33,$AA$3:$AA33) -> 163.53798 | AD34: =_xlfn.FORECAST.LINEAR($AA34,AD$3:AD33,$AA$3:$AA33) -> 160.76201 | AE34: =_xlfn.FORECAST.LINEAR($AA34,AE$3:AE33,$AA$3:$AA33) -> 84.146078 | AF34: =_xlfn.FORECAST.LINEAR($AA34,AF$3:AF33,$AA$3:$AA33) -> 144479.81 | AH34: 46235 | AI34: =IFERROR(AVERAGE(OFFSET(AI33,-$I$6+1,0,$I$6,1)),"") -> 103.96035 | AJ34: =IFERROR(AVERAGE(OFFSET(AJ33,-$I$6+1,0,$I$6,1)),"") -> 134.70703 | AK34: =IFERROR(AVERAGE(OFFSET(AK33,-$I$6+1,0,$I$6,1)),"") -> 129.97885 | AL34: =IFERROR(AVERAGE(OFFSET(AL33,-$I$6+1,0,$I$6,1)),"") -> 68.435296 | AM34: =IFERROR(AVERAGE(OFFSET(AM33,-$I$6+1,0,$I$6,1)),"") -> 115348.67 | AO34: 46174 | AP34: =IFERROR(AP33*$G$6+(1-$G$6)*AVERAGE(AP17:AP33),"") -> 90.633558 | AQ34: =IFERROR(AQ33*$G$6+(1-$G$6)*AVERAGE(AQ17:AQ33),"") -> 120.54904 | AR34: =IFERROR(AR33*$G$6+(1-$G$6)*AVERAGE(AR17:AR33),"") -> 112.63849 | AS34: =IFERROR(AS33*$G$6+(1-$G$6)*AVERAGE(AS17:AS33),"") -> 62.04986 | AT34: =IFERROR(AT33*$G$6+(1-$G$6)*AVERAGE(AT17:AT33),"") -> 99836.217
AA35: 46266 | AB35: =_xlfn.FORECAST.LINEAR($AA35,AB$3:AB34,$AA$3:$AA34) -> 130.43731 | AC35: =_xlfn.FORECAST.LINEAR($AA35,AC$3:AC34,$AA$3:$AA34) -> 166.0184 | AD35: =_xlfn.FORECAST.LINEAR($AA35,AD$3:AD34,$AA$3:$AA34) -> 163.48064 | AE35: =_xlfn.FORECAST.LINEAR($AA35,AE$3:AE34,$AA$3:$AA34) -> 85.508357 | AF35: =_xlfn.FORECAST.LINEAR($AA35,AF$3:AF34,$AA$3:$AA34) -> 146895.25 | AH35: 46266 | AI35: =IFERROR(AVERAGE(OFFSET(AI34,-$I$6+1,0,$I$6,1)),"") -> 103.95705 | AJ35: =IFERROR(AVERAGE(OFFSET(AJ34,-$I$6+1,0,$I$6,1)),"") -> 134.68262 | AK35: =IFERROR(AVERAGE(OFFSET(AK34,-$I$6+1,0,$I$6,1)),"") -> 129.97709 | AL35: =IFERROR(AVERAGE(OFFSET(AL34,-$I$6+1,0,$I$6,1)),"") -> 68.388237 | AM35: =IFERROR(AVERAGE(OFFSET(AM34,-$I$6+1,0,$I$6,1)),"") -> 117446.89 | AO35: 46204 | AP35: =IFERROR(AP34*$G$6+(1-$G$6)*AVERAGE(AP18:AP34),"") -> 90.728186 | AQ35: =IFERROR(AQ34*$G$6+(1-$G$6)*AVERAGE(AQ18:AQ34),"") -> 120.6562 | AR35: =IFERROR(AR34*$G$6+(1-$G$6)*AVERAGE(AR18:AR34),"") -> 112.76886 | AS35: =IFERROR(AS34*$G$6+(1-$G$6)*AVERAGE(AS18:AS34),"") -> 62.21574 | AT35: =IFERROR(AT34*$G$6+(1-$G$6)*AVERAGE(AT18:AT34),"") -> 100041.74
AA36: 46296 | AB36: =_xlfn.FORECAST.LINEAR($AA36,AB$3:AB35,$AA$3:$AA35) -> 132.50534 | AC36: =_xlfn.FORECAST.LINEAR($AA36,AC$3:AC35,$AA$3:$AA35) -> 168.4188 | AD36: =_xlfn.FORECAST.LINEAR($AA36,AD$3:AD35,$AA$3:$AA35) -> 166.11157 | AE36: =_xlfn.FORECAST.LINEAR($AA36,AE$3:AE35,$AA$3:$AA35) -> 86.826692 | AF36: =_xlfn.FORECAST.LINEAR($AA36,AF$3:AF35,$AA$3:$AA35) -> 149232.77 | AH36: 46296 | AI36: =IFERROR(AVERAGE(OFFSET(AI35,-$I$6+1,0,$I$6,1)),"") -> 104.12014 | AJ36: =IFERROR(AVERAGE(OFFSET(AJ35,-$I$6+1,0,$I$6,1)),"") -> 134.82284 | AK36: =IFERROR(AVERAGE(OFFSET(AK35,-$I$6+1,0,$I$6,1)),"") -> 130.22518 | AL36: =IFERROR(AVERAGE(OFFSET(AL35,-$I$6+1,0,$I$6,1)),"") -> 68.253924 | AM36: =IFERROR(AVERAGE(OFFSET(AM35,-$I$6+1,0,$I$6,1)),"") -> 118218.3 | AO36: 46235 | AP36: =IFERROR(AP35*$G$6+(1-$G$6)*AVERAGE(AP19:AP35),"") -> 90.753632 | AQ36: =IFERROR(AQ35*$G$6+(1-$G$6)*AVERAGE(AQ19:AQ35),"") -> 120.65552 | AR36: =IFERROR(AR35*$G$6+(1-$G$6)*AVERAGE(AR19:AR35),"") -> 112.77632 | AS36: =IFERROR(AS35*$G$6+(1-$G$6)*AVERAGE(AS19:AS35),"") -> 62.339217 | AT36: =IFERROR(AT35*$G$6+(1-$G$6)*AVERAGE(AT19:AT35),"") -> 99855.707
AA37: 46327 | AB37: =_xlfn.FORECAST.LINEAR($AA37,AB$3:AB36,$AA$3:$AA36) -> 134.64229 | AC37: =_xlfn.FORECAST.LINEAR($AA37,AC$3:AC36,$AA$3:$AA36) -> 170.89922 | AD37: =_xlfn.FORECAST.LINEAR($AA37,AD$3:AD36,$AA$3:$AA36) -> 168.8302 | AE37: =_xlfn.FORECAST.LINEAR($AA37,AE$3:AE36,$AA$3:$AA36) -> 88.188971 | AF37: =_xlfn.FORECAST.LINEAR($AA37,AF$3:AF36,$AA$3:$AA36) -> 151648.21 | AH37: 46327 | AI37: =IFERROR(AVERAGE(OFFSET(AI36,-$I$6+1,0,$I$6,1)),"") -> 103.88015 | AJ37: =IFERROR(AVERAGE(OFFSET(AJ36,-$I$6+1,0,$I$6,1)),"") -> 134.64141 | AK37: =IFERROR(AVERAGE(OFFSET(AK36,-$I$6+1,0,$I$6,1)),"") -> 129.99394 | AL37: =IFERROR(AVERAGE(OFFSET(AL36,-$I$6+1,0,$I$6,1)),"") -> 67.941751 | AM37: =IFERROR(AVERAGE(OFFSET(AM36,-$I$6+1,0,$I$6,1)),"") -> 115291.49 | AO37: 46266 | AP37: =IFERROR(AP36*$G$6+(1-$G$6)*AVERAGE(AP20:AP36),"") -> 90.676973 | AQ37: =IFERROR(AQ36*$G$6+(1-$G$6)*AVERAGE(AQ20:AQ36),"") -> 120.54505 | AR37: =IFERROR(AR36*$G$6+(1-$G$6)*AVERAGE(AR20:AR36),"") -> 112.66201 | AS37: =IFERROR(AS36*$G$6+(1-$G$6)*AVERAGE(AS20:AS36),"") -> 62.336107 | AT37: =IFERROR(AT36*$G$6+(1-$G$6)*AVERAGE(AT20:AT36),"") -> 99698.242
AA38: 46357 | AB38: =_xlfn.FORECAST.LINEAR($AA38,AB$3:AB37,$AA$3:$AA37) -> 136.71032 | AC38: =_xlfn.FORECAST.LINEAR($AA38,AC$3:AC37,$AA$3:$AA37) -> 173.29963 | AD38: =_xlfn.FORECAST.LINEAR($AA38,AD$3:AD37,$AA$3:$AA37) -> 171.46113 | AE38: =_xlfn.FORECAST.LINEAR($AA38,AE$3:AE37,$AA$3:$AA37) -> 89.507305 | AF38: =_xlfn.FORECAST.LINEAR($AA38,AF$3:AF37,$AA$3:$AA37) -> 153985.73 | AH38: 46357 | AI38: =IFERROR(AVERAGE(OFFSET(AI37,-$I$6+1,0,$I$6,1)),"") -> 103.53683 | AJ38: =IFERROR(AVERAGE(OFFSET(AJ37,-$I$6+1,0,$I$6,1)),"") -> 134.36152 | AK38: =IFERROR(AVERAGE(OFFSET(AK37,-$I$6+1,0,$I$6,1)),"") -> 129.49344 | AL38: =IFERROR(AVERAGE(OFFSET(AL37,-$I$6+1,0,$I$6,1)),"") -> 68.52023 | AM38: =IFERROR(AVERAGE(OFFSET(AM37,-$I$6+1,0,$I$6,1)),"") -> 115424.12 | AO38: 46296 | AP38: =IFERROR(AP37*$G$6+(1-$G$6)*AVERAGE(AP21:AP37),"") -> 90.561464 | AQ38: =IFERROR(AQ37*$G$6+(1-$G$6)*AVERAGE(AQ21:AQ37),"") -> 120.39665 | AR38: =IFERROR(AR37*$G$6+(1-$G$6)*AVERAGE(AR21:AR37),"") -> 112.50361 | AS38: =IFERROR(AS37*$G$6+(1-$G$6)*AVERAGE(AS21:AS37),"") -> 62.272106 | AT38: =IFERROR(AT37*$G$6+(1-$G$6)*AVERAGE(AT21:AT37),"") -> 99583.123
AA39: 46388 | AB39: =_xlfn.FORECAST.LINEAR($AA39,AB$3:AB38,$AA$3:$AA38) -> 138.84728 | AC39: =_xlfn.FORECAST.LINEAR($AA39,AC$3:AC38,$AA$3:$AA38) -> 175.78004 | AD39: =_xlfn.FORECAST.LINEAR($AA39,AD$3:AD38,$AA$3:$AA38) -> 174.17975 | AE39: =_xlfn.FORECAST.LINEAR($AA39,AE$3:AE38,$AA$3:$AA38) -> 90.869585 | AF39: =_xlfn.FORECAST.LINEAR($AA39,AF$3:AF38,$AA$3:$AA38) -> 156401.17 | AH39: 46388 | AI39: =IFERROR(AVERAGE(OFFSET(AI38,-$I$6+1,0,$I$6,1)),"") -> 102.83156 | AJ39: =IFERROR(AVERAGE(OFFSET(AJ38,-$I$6+1,0,$I$6,1)),"") -> 133.64165 | AK39: =IFERROR(AVERAGE(OFFSET(AK38,-$I$6+1,0,$I$6,1)),"") -> 128.61789 | AL39: =IFERROR(AVERAGE(OFFSET(AL38,-$I$6+1,0,$I$6,1)),"") -> 67.813583 | AM39: =IFERROR(AVERAGE(OFFSET(AM38,-$I$6+1,0,$I$6,1)),"") -> 114050.29 | AO39: 46327 | AP39: =IFERROR(AP38*$G$6+(1-$G$6)*AVERAGE(AP22:AP38),"") -> 90.443624 | AQ39: =IFERROR(AQ38*$G$6+(1-$G$6)*AVERAGE(AQ22:AQ38),"") -> 120.25122 | AR39: =IFERROR(AR38*$G$6+(1-$G$6)*AVERAGE(AR22:AR38),"") -> 112.34567 | AS39: =IFERROR(AS38*$G$6+(1-$G$6)*AVERAGE(AS22:AS38),"") -> 62.187434 | AT39: =IFERROR(AT38*$G$6+(1-$G$6)*AVERAGE(AT22:AT38),"") -> 99513.78
AA40: 46419 | AB40: =_xlfn.FORECAST.LINEAR($AA40,AB$3:AB39,$AA$3:$AA39) -> 140.98424 | AC40: =_xlfn.FORECAST.LINEAR($AA40,AC$3:AC39,$AA$3:$AA39) -> 178.26046 | AD40: =_xlfn.FORECAST.LINEAR($AA40,AD$3:AD39,$AA$3:$AA39) -> 176.89838 | AE40: =_xlfn.FORECAST.LINEAR($AA40,AE$3:AE39,$AA$3:$AA39) -> 92.231864 | AF40: =_xlfn.FORECAST.LINEAR($AA40,AF$3:AF39,$AA$3:$AA39) -> 158816.6 | AH40: 46419 | AI40: =IFERROR(AVERAGE(OFFSET(AI39,-$I$6+1,0,$I$6,1)),"") -> 103.06753 | AJ40: =IFERROR(AVERAGE(OFFSET(AJ39,-$I$6+1,0,$I$6,1)),"") -> 133.88262 | AK40: =IFERROR(AVERAGE(OFFSET(AK39,-$I$6+1,0,$I$6,1)),"") -> 128.91938 | AL40: =IFERROR(AVERAGE(OFFSET(AL39,-$I$6+1,0,$I$6,1)),"") -> 67.950826 | AM40: =IFERROR(AVERAGE(OFFSET(AM39,-$I$6+1,0,$I$6,1)),"") -> 114505.25 | AO40: 46357 | AP40: =IFERROR(AP39*$G$6+(1-$G$6)*AVERAGE(AP23:AP39),"") -> 90.342503 | AQ40: =IFERROR(AQ39*$G$6+(1-$G$6)*AVERAGE(AQ23:AQ39),"") -> 120.12945 | AR40: =IFERROR(AR39*$G$6+(1-$G$6)*AVERAGE(AR23:AR39),"") -> 112.21146 | AS40: =IFERROR(AS39*$G$6+(1-$G$6)*AVERAGE(AS23:AS39),"") -> 62.104786 | AT40: =IFERROR(AT39*$G$6+(1-$G$6)*AVERAGE(AT23:AT39),"") -> 99487.152
... AA48: 46661 | AB48: =_xlfn.FORECAST.LINEAR($AA48,AB$3:AB47,$AA$3:$AA47) -> 157.6663 | AC48: =_xlfn.FORECAST.LINEAR($AA48,AC$3:AC47,$AA$3:$AA47) -> 197.62372 | AD48: =_xlfn.FORECAST.LINEAR($AA48,AD$3:AD47,$AA$3:$AA47) -> 198.12121 | AE48: =_xlfn.FORECAST.LINEAR($AA48,AE$3:AE47,$AA$3:$AA47) -> 102.86643 | AF48: =_xlfn.FORECAST.LINEAR($AA48,AF$3:AF47,$AA$3:$AA47) -> 177672.6 | AH48: 46661 | AI48: =IFERROR(AVERAGE(OFFSET(AI47,-$I$6+1,0,$I$6,1)),"") -> 103.4778 | AJ48: =IFERROR(AVERAGE(OFFSET(AJ47,-$I$6+1,0,$I$6,1)),"") -> 134.25869 | AK48: =IFERROR(AVERAGE(OFFSET(AK47,-$I$6+1,0,$I$6,1)),"") -> 129.42626 | AL48: =IFERROR(AVERAGE(OFFSET(AL47,-$I$6+1,0,$I$6,1)),"") -> 68.112934 | AM48: =IFERROR(AVERAGE(OFFSET(AM47,-$I$6+1,0,$I$6,1)),"") -> 115325.63 | AO48: 46600 | AP48: =IFERROR(AP47*$G$6+(1-$G$6)*AVERAGE(AP31:AP47),"") -> 90.269625 | AQ48: =IFERROR(AQ47*$G$6+(1-$G$6)*AVERAGE(AQ31:AQ47),"") -> 120.06291 | AR48: =IFERROR(AR47*$G$6+(1-$G$6)*AVERAGE(AR31:AR47),"") -> 112.11736 | AS48: =IFERROR(AS47*$G$6+(1-$G$6)*AVERAGE(AS31:AS47),"") -> 61.94516 | AT48: =IFERROR(AT47*$G$6+(1-$G$6)*AVERAGE(AT31:AT47),"") -> 99616.374
B49: 24-Month Leads-to-Won Forecast | AA49: 46692 | AB49: =_xlfn.FORECAST.LINEAR($AA49,AB$3:AB48,$AA$3:$AA48) -> 159.80325 | AC49: =_xlfn.FORECAST.LINEAR($AA49,AC$3:AC48,$AA$3:$AA48) -> 200.10413 | AD49: =_xlfn.FORECAST.LINEAR($AA49,AD$3:AD48,$AA$3:$AA48) -> 200.83984 | AE49: =_xlfn.FORECAST.LINEAR($AA49,AE$3:AE48,$AA$3:$AA48) -> 104.22871 | AF49: =_xlfn.FORECAST.LINEAR($AA49,AF$3:AF48,$AA$3:$AA48) -> 180088.04 | AH49: 46692 | AI49: =IFERROR(AVERAGE(OFFSET(AI48,-$I$6+1,0,$I$6,1)),"") -> 103.42427 | AJ49: =IFERROR(AVERAGE(OFFSET(AJ48,-$I$6+1,0,$I$6,1)),"") -> 134.21168 | AK49: =IFERROR(AVERAGE(OFFSET(AK48,-$I$6+1,0,$I$6,1)),"") -> 129.35968 | AL49: =IFERROR(AVERAGE(OFFSET(AL48,-$I$6+1,0,$I$6,1)),"") -> 68.101184 | AM49: =IFERROR(AVERAGE(OFFSET(AM48,-$I$6+1,0,$I$6,1)),"") -> 115084.57 | AO49: 46631 | AP49: =IFERROR(AP48*$G$6+(1-$G$6)*AVERAGE(AP32:AP48),"") -> 90.294208 | AQ49: =IFERROR(AQ48*$G$6+(1-$G$6)*AVERAGE(AQ32:AQ48),"") -> 120.09287 | AR49: =IFERROR(AR48*$G$6+(1-$G$6)*AVERAGE(AR32:AR48),"") -> 112.15104 | AS49: =IFERROR(AS48*$G$6+(1-$G$6)*AVERAGE(AS32:AS48),"") -> 61.963867 | AT49: =IFERROR(AT48*$G$6+(1-$G$6)*AVERAGE(AT32:AT48),"") -> 99618.075
AA50: 46722 | AB50: =_xlfn.FORECAST.LINEAR($AA50,AB$3:AB49,$AA$3:$AA49) -> 161.87128 | AC50: =_xlfn.FORECAST.LINEAR($AA50,AC$3:AC49,$AA$3:$AA49) -> 202.50454 | AD50: =_xlfn.FORECAST.LINEAR($AA50,AD$3:AD49,$AA$3:$AA49) -> 203.47077 | AE50: =_xlfn.FORECAST.LINEAR($AA50,AE$3:AE49,$AA$3:$AA49) -> 105.54704 | AF50: =_xlfn.FORECAST.LINEAR($AA50,AF$3:AF49,$AA$3:$AA49) -> 182425.56 | AH50: 46722 | AI50: =IFERROR(AVERAGE(OFFSET(AI49,-$I$6+1,0,$I$6,1)),"") -> 103.38628 | AJ50: =IFERROR(AVERAGE(OFFSET(AJ49,-$I$6+1,0,$I$6,1)),"") -> 134.17586 | AK50: =IFERROR(AVERAGE(OFFSET(AK49,-$I$6+1,0,$I$6,1)),"") -> 129.30683 | AL50: =IFERROR(AVERAGE(OFFSET(AL49,-$I$6+1,0,$I$6,1)),"") -> 68.11447 | AM50: =IFERROR(AVERAGE(OFFSET(AM49,-$I$6+1,0,$I$6,1)),"") -> 115067.33 | AO50: 46661 | AP50: =IFERROR(AP49*$G$6+(1-$G$6)*AVERAGE(AP33:AP49),"") -> 90.314197 | AQ50: =IFERROR(AQ49*$G$6+(1-$G$6)*AVERAGE(AQ33:AQ49),"") -> 120.11686 | AR50: =IFERROR(AR49*$G$6+(1-$G$6)*AVERAGE(AR33:AR49),"") -> 112.17853 | AS50: =IFERROR(AS49*$G$6+(1-$G$6)*AVERAGE(AS33:AS49),"") -> 61.982614 | AT50: =IFERROR(AT49*$G$6+(1-$G$6)*AVERAGE(AT33:AT49),"") -> 99622.189
